[{"colonia":"Batán Chico","col-slug":"batan-chico","asentamiento":"Ranchería","cp":"51045","estado":"Estado de México","estado-slug":"estado-de-mexico","url":"https:\/\/cp.guiapaqueteria.com\/codigos-postales\/estado-de-mexico\/batan-chico\/"},{"colonia":"Batán Grande","col-slug":"batan-grande","asentamiento":"Ranchería","cp":"51045","estado":"Estado de México","estado-slug":"estado-de-mexico","url":"https:\/\/cp.guiapaqueteria.com\/codigos-postales\/estado-de-mexico\/batan-grande\/"},{"colonia":"Cabecera de Indígenas Primer Cuartel","col-slug":"cabecera-de-indigenas-primer-cuartel","asentamiento":"Pueblo","cp":"51030","estado":"Estado de México","estado-slug":"estado-de-mexico","url":"https:\/\/cp.guiapaqueteria.com\/codigos-postales\/estado-de-mexico\/cabecera-de-indigenas-primer-cuartel\/"},{"colonia":"Cabecera de Indígenas Segundo Cuartel","col-slug":"cabecera-de-indigenas-segundo-cuartel","asentamiento":"Pueblo","cp":"51030","estado":"Estado de México","estado-slug":"estado-de-mexico","url":"https:\/\/cp.guiapaqueteria.com\/codigos-postales\/estado-de-mexico\/cabecera-de-indigenas-segundo-cuartel\/"},{"colonia":"De Arriba de San Juan Xoconusco","col-slug":"de-arriba-de-san-juan-xoconusco","asentamiento":"Barrio","cp":"51050","estado":"Estado de México","estado-slug":"estado-de-mexico","url":"https:\/\/cp.guiapaqueteria.com\/codigos-postales\/estado-de-mexico\/de-arriba-de-san-juan-xoconusco\/"},{"colonia":"Donato Guerra","col-slug":"donato-guerra","asentamiento":"Pueblo","cp":"51030","estado":"Estado de México","estado-slug":"estado-de-mexico","url":"https:\/\/cp.guiapaqueteria.com\/codigos-postales\/estado-de-mexico\/donato-guerra\/"},{"colonia":"El Capulín","col-slug":"el-capulin","asentamiento":"Ranchería","cp":"51055","estado":"Estado de México","estado-slug":"estado-de-mexico","url":"https:\/\/cp.guiapaqueteria.com\/codigos-postales\/estado-de-mexico\/el-capulin\/"},{"colonia":"La Fundición","col-slug":"la-fundicion","asentamiento":"Ranchería","cp":"51055","estado":"Estado de México","estado-slug":"estado-de-mexico","url":"https:\/\/cp.guiapaqueteria.com\/codigos-postales\/estado-de-mexico\/la-fundicion\/"},{"colonia":"Llano Redondo de Zaragoza (Llano Redondo)","col-slug":"llano-redondo-de-zaragoza-llano-redondo","asentamiento":"Ranchería","cp":"51055","estado":"Estado de México","estado-slug":"estado-de-mexico","url":"https:\/\/cp.guiapaqueteria.com\/codigos-postales\/estado-de-mexico\/llano-redondo-de-zaragoza-llano-redondo\/"},{"colonia":"Macheros","col-slug":"macheros","asentamiento":"Ranchería","cp":"51055","estado":"Estado de México","estado-slug":"estado-de-mexico","url":"https:\/\/cp.guiapaqueteria.com\/codigos-postales\/estado-de-mexico\/macheros\/"},{"colonia":"Mesas Altas de Xoconusco","col-slug":"mesas-altas-de-xoconusco","asentamiento":"Pueblo","cp":"51054","estado":"Estado de México","estado-slug":"estado-de-mexico","url":"https:\/\/cp.guiapaqueteria.com\/codigos-postales\/estado-de-mexico\/mesas-altas-de-xoconusco\/"},{"colonia":"Puerto de la Cruz","col-slug":"puerto-de-la-cruz","asentamiento":"Rancho","cp":"51044","estado":"Estado de México","estado-slug":"estado-de-mexico","url":"https:\/\/cp.guiapaqueteria.com\/codigos-postales\/estado-de-mexico\/puerto-de-la-cruz\/"},{"colonia":"San Agustín de las Palmas","col-slug":"san-agustin-de-las-palmas","asentamiento":"Pueblo","cp":"51030","estado":"Estado de México","estado-slug":"estado-de-mexico","url":"https:\/\/cp.guiapaqueteria.com\/codigos-postales\/estado-de-mexico\/san-agustin-de-las-palmas\/"},{"colonia":"San Antonio de la Laguna","col-slug":"san-antonio-de-la-laguna","asentamiento":"Pueblo","cp":"51043","estado":"Estado de México","estado-slug":"estado-de-mexico","url":"https:\/\/cp.guiapaqueteria.com\/codigos-postales\/estado-de-mexico\/san-antonio-de-la-laguna\/"},{"colonia":"San Antonio Hidalgo (Ranchería de San Antonio)","col-slug":"san-antonio-hidalgo-rancheria-de-san-antonio","asentamiento":"Ranchería","cp":"51044","estado":"Estado de México","estado-slug":"estado-de-mexico","url":"https:\/\/cp.guiapaqueteria.com\/codigos-postales\/estado-de-mexico\/san-antonio-hidalgo-rancheria-de-san-antonio\/"},{"colonia":"San Francisco Mihualtepec","col-slug":"san-francisco-mihualtepec","asentamiento":"Pueblo","cp":"51046","estado":"Estado de México","estado-slug":"estado-de-mexico","url":"https:\/\/cp.guiapaqueteria.com\/codigos-postales\/estado-de-mexico\/san-francisco-mihualtepec\/"},{"colonia":"San Juan Xoconusco","col-slug":"san-juan-xoconusco","asentamiento":"Pueblo","cp":"51050","estado":"Estado de México","estado-slug":"estado-de-mexico","url":"https:\/\/cp.guiapaqueteria.com\/codigos-postales\/estado-de-mexico\/san-juan-xoconusco\/"},{"colonia":"San Lucas Texcaltitlán","col-slug":"san-lucas-texcaltitlan","asentamiento":"Pueblo","cp":"51034","estado":"Estado de México","estado-slug":"estado-de-mexico","url":"https:\/\/cp.guiapaqueteria.com\/codigos-postales\/estado-de-mexico\/san-lucas-texcaltitlan\/"},{"colonia":"San Lucas Texcaltitlán (Sabanillas)","col-slug":"san-lucas-texcaltitlan-sabanillas","asentamiento":"Ejido","cp":"51035","estado":"Estado de México","estado-slug":"estado-de-mexico","url":"https:\/\/cp.guiapaqueteria.com\/codigos-postales\/estado-de-mexico\/san-lucas-texcaltitlan-sabanillas\/"},{"colonia":"San Martín Obispo","col-slug":"san-martin-obispo","asentamiento":"Ranchería","cp":"51044","estado":"Estado de México","estado-slug":"estado-de-mexico","url":"https:\/\/cp.guiapaqueteria.com\/codigos-postales\/estado-de-mexico\/san-martin-obispo\/"},{"colonia":"San Martín Obispo (San Martín San Pedro)","col-slug":"san-martin-obispo-san-martin-san-pedro","asentamiento":"Pueblo","cp":"51044","estado":"Estado de México","estado-slug":"estado-de-mexico","url":"https:\/\/cp.guiapaqueteria.com\/codigos-postales\/estado-de-mexico\/san-martin-obispo-san-martin-san-pedro\/"},{"colonia":"San Miguel Xooltepec","col-slug":"san-miguel-xooltepec","asentamiento":"Pueblo","cp":"51046","estado":"Estado de México","estado-slug":"estado-de-mexico","url":"https:\/\/cp.guiapaqueteria.com\/codigos-postales\/estado-de-mexico\/san-miguel-xooltepec\/"},{"colonia":"San Simón de la Laguna","col-slug":"san-simon-de-la-laguna","asentamiento":"Pueblo","cp":"51040","estado":"Estado de México","estado-slug":"estado-de-mexico","url":"https:\/\/cp.guiapaqueteria.com\/codigos-postales\/estado-de-mexico\/san-simon-de-la-laguna\/"},{"colonia":"Santiago Huitlapaltepec","col-slug":"santiago-huitlapaltepec","asentamiento":"Pueblo","cp":"51035","estado":"Estado de México","estado-slug":"estado-de-mexico","url":"https:\/\/cp.guiapaqueteria.com\/codigos-postales\/estado-de-mexico\/santiago-huitlapaltepec\/"}]