[{"colonia":"20 de Noviembre","col-slug":"20-de-noviembre","asentamiento":"Colonia","cp":"45404","estado":"Jalisco","estado-slug":"jalisco","url":"https:\/\/cp.guiapaqueteria.com\/codigos-postales\/jalisco\/20-de-noviembre\/"},{"colonia":"Adobera","col-slug":"adobera","asentamiento":"Colonia","cp":"45404","estado":"Jalisco","estado-slug":"jalisco","url":"https:\/\/cp.guiapaqueteria.com\/codigos-postales\/jalisco\/adobera\/"},{"colonia":"Agua Blanca","col-slug":"agua-blanca","asentamiento":"Ranchería","cp":"45427","estado":"Jalisco","estado-slug":"jalisco","url":"https:\/\/cp.guiapaqueteria.com\/codigos-postales\/jalisco\/agua-blanca\/"},{"colonia":"Agua Escondida","col-slug":"agua-escondida","asentamiento":"Colonia","cp":"45403","estado":"Jalisco","estado-slug":"jalisco","url":"https:\/\/cp.guiapaqueteria.com\/codigos-postales\/jalisco\/agua-escondida\/"},{"colonia":"Aguajomate","col-slug":"aguajomate","asentamiento":"Colonia","cp":"45404","estado":"Jalisco","estado-slug":"jalisco","url":"https:\/\/cp.guiapaqueteria.com\/codigos-postales\/jalisco\/aguajomate\/"},{"colonia":"Águilas","col-slug":"aguilas","asentamiento":"Colonia","cp":"45404","estado":"Jalisco","estado-slug":"jalisco","url":"https:\/\/cp.guiapaqueteria.com\/codigos-postales\/jalisco\/aguilas\/"},{"colonia":"Ahuacate","col-slug":"ahuacate","asentamiento":"Colonia","cp":"45405","estado":"Jalisco","estado-slug":"jalisco","url":"https:\/\/cp.guiapaqueteria.com\/codigos-postales\/jalisco\/ahuacate\/"},{"colonia":"Alamedas de San Gaspar","col-slug":"alamedas-de-san-gaspar","asentamiento":"Colonia","cp":"45408","estado":"Jalisco","estado-slug":"jalisco","url":"https:\/\/cp.guiapaqueteria.com\/codigos-postales\/jalisco\/alamedas-de-san-gaspar\/"},{"colonia":"Alamedas de Zalatitán","col-slug":"alamedas-de-zalatitan","asentamiento":"Colonia","cp":"45407","estado":"Jalisco","estado-slug":"jalisco","url":"https:\/\/cp.guiapaqueteria.com\/codigos-postales\/jalisco\/alamedas-de-zalatitan\/"},{"colonia":"Alfareros","col-slug":"alfareros","asentamiento":"Colonia","cp":"45402","estado":"Jalisco","estado-slug":"jalisco","url":"https:\/\/cp.guiapaqueteria.com\/codigos-postales\/jalisco\/alfareros\/"},{"colonia":"Alpinos","col-slug":"alpinos","asentamiento":"Colonia","cp":"45402","estado":"Jalisco","estado-slug":"jalisco","url":"https:\/\/cp.guiapaqueteria.com\/codigos-postales\/jalisco\/alpinos\/"},{"colonia":"Altamira","col-slug":"altamira","asentamiento":"Colonia","cp":"45400","estado":"Jalisco","estado-slug":"jalisco","url":"https:\/\/cp.guiapaqueteria.com\/codigos-postales\/jalisco\/altamira\/"},{"colonia":"Altamira","col-slug":"altamira","asentamiento":"Colonia","cp":"45405","estado":"Jalisco","estado-slug":"jalisco","url":"https:\/\/cp.guiapaqueteria.com\/codigos-postales\/jalisco\/altamira\/"},{"colonia":"Amiales Ciudad Aztlán","col-slug":"amiales-ciudad-aztlan","asentamiento":"Colonia","cp":"45402","estado":"Jalisco","estado-slug":"jalisco","url":"https:\/\/cp.guiapaqueteria.com\/codigos-postales\/jalisco\/amiales-ciudad-aztlan\/"},{"colonia":"Arboleda Tonala","col-slug":"arboleda-tonala","asentamiento":"Fraccionamiento","cp":"45410","estado":"Jalisco","estado-slug":"jalisco","url":"https:\/\/cp.guiapaqueteria.com\/codigos-postales\/jalisco\/arboleda-tonala\/"},{"colonia":"Arboledas de San Gaspar","col-slug":"arboledas-de-san-gaspar","asentamiento":"Colonia","cp":"45408","estado":"Jalisco","estado-slug":"jalisco","url":"https:\/\/cp.guiapaqueteria.com\/codigos-postales\/jalisco\/arboledas-de-san-gaspar\/"},{"colonia":"Arcos de Zalatitan","col-slug":"arcos-de-zalatitan","asentamiento":"Fraccionamiento","cp":"45406","estado":"Jalisco","estado-slug":"jalisco","url":"https:\/\/cp.guiapaqueteria.com\/codigos-postales\/jalisco\/arcos-de-zalatitan\/"},{"colonia":"Arcos de Zalatitan II","col-slug":"arcos-de-zalatitan-ii","asentamiento":"Colonia","cp":"45406","estado":"Jalisco","estado-slug":"jalisco","url":"https:\/\/cp.guiapaqueteria.com\/codigos-postales\/jalisco\/arcos-de-zalatitan-ii\/"},{"colonia":"Arroyo de Enmedio","col-slug":"arroyo-de-enmedio","asentamiento":"Colonia","cp":"45426","estado":"Jalisco","estado-slug":"jalisco","url":"https:\/\/cp.guiapaqueteria.com\/codigos-postales\/jalisco\/arroyo-de-enmedio\/"},{"colonia":"Arroyo Seco","col-slug":"arroyo-seco","asentamiento":"Colonia","cp":"45406","estado":"Jalisco","estado-slug":"jalisco","url":"https:\/\/cp.guiapaqueteria.com\/codigos-postales\/jalisco\/arroyo-seco\/"},{"colonia":"Arroyos","col-slug":"arroyos","asentamiento":"Colonia","cp":"45400","estado":"Jalisco","estado-slug":"jalisco","url":"https:\/\/cp.guiapaqueteria.com\/codigos-postales\/jalisco\/arroyos\/"},{"colonia":"Bajío de la Mesa","col-slug":"bajio-de-la-mesa","asentamiento":"Colonia","cp":"45400","estado":"Jalisco","estado-slug":"jalisco","url":"https:\/\/cp.guiapaqueteria.com\/codigos-postales\/jalisco\/bajio-de-la-mesa\/"},{"colonia":"Bajío San Gaspar","col-slug":"bajio-san-gaspar","asentamiento":"Colonia","cp":"45408","estado":"Jalisco","estado-slug":"jalisco","url":"https:\/\/cp.guiapaqueteria.com\/codigos-postales\/jalisco\/bajio-san-gaspar\/"},{"colonia":"Balcones del Rosario","col-slug":"balcones-del-rosario","asentamiento":"Colonia","cp":"45404","estado":"Jalisco","estado-slug":"jalisco","url":"https:\/\/cp.guiapaqueteria.com\/codigos-postales\/jalisco\/balcones-del-rosario\/"},{"colonia":"Balcones Del Sol","col-slug":"balcones-del-sol","asentamiento":"Colonia","cp":"45400","estado":"Jalisco","estado-slug":"jalisco","url":"https:\/\/cp.guiapaqueteria.com\/codigos-postales\/jalisco\/balcones-del-sol\/"},{"colonia":"Barrio Nuevo","col-slug":"barrio-nuevo","asentamiento":"Colonia","cp":"45402","estado":"Jalisco","estado-slug":"jalisco","url":"https:\/\/cp.guiapaqueteria.com\/codigos-postales\/jalisco\/barrio-nuevo\/"},{"colonia":"Basilio Badillo","col-slug":"basilio-badillo","asentamiento":"Colonia","cp":"45406","estado":"Jalisco","estado-slug":"jalisco","url":"https:\/\/cp.guiapaqueteria.com\/codigos-postales\/jalisco\/basilio-badillo\/"},{"colonia":"Basilio Badillo II","col-slug":"basilio-badillo-ii","asentamiento":"Colonia","cp":"45404","estado":"Jalisco","estado-slug":"jalisco","url":"https:\/\/cp.guiapaqueteria.com\/codigos-postales\/jalisco\/basilio-badillo-ii\/"},{"colonia":"Bellavista","col-slug":"bellavista","asentamiento":"Colonia","cp":"45400","estado":"Jalisco","estado-slug":"jalisco","url":"https:\/\/cp.guiapaqueteria.com\/codigos-postales\/jalisco\/bellavista\/"},{"colonia":"Bosques de Tonalá","col-slug":"bosques-de-tonala","asentamiento":"Colonia","cp":"45404","estado":"Jalisco","estado-slug":"jalisco","url":"https:\/\/cp.guiapaqueteria.com\/codigos-postales\/jalisco\/bosques-de-tonala\/"},{"colonia":"Bosques del Sol","col-slug":"bosques-del-sol","asentamiento":"Colonia","cp":"45422","estado":"Jalisco","estado-slug":"jalisco","url":"https:\/\/cp.guiapaqueteria.com\/codigos-postales\/jalisco\/bosques-del-sol\/"},{"colonia":"Buena Mirada","col-slug":"buena-mirada","asentamiento":"Fraccionamiento","cp":"45410","estado":"Jalisco","estado-slug":"jalisco","url":"https:\/\/cp.guiapaqueteria.com\/codigos-postales\/jalisco\/buena-mirada\/"},{"colonia":"Buenavista I","col-slug":"buenavista-i","asentamiento":"Colonia","cp":"45404","estado":"Jalisco","estado-slug":"jalisco","url":"https:\/\/cp.guiapaqueteria.com\/codigos-postales\/jalisco\/buenavista-i\/"},{"colonia":"Buenavista II","col-slug":"buenavista-ii","asentamiento":"Colonia","cp":"45404","estado":"Jalisco","estado-slug":"jalisco","url":"https:\/\/cp.guiapaqueteria.com\/codigos-postales\/jalisco\/buenavista-ii\/"},{"colonia":"Buenos Aires","col-slug":"buenos-aires","asentamiento":"Fraccionamiento","cp":"45400","estado":"Jalisco","estado-slug":"jalisco","url":"https:\/\/cp.guiapaqueteria.com\/codigos-postales\/jalisco\/buenos-aires\/"},{"colonia":"Cañada Real","col-slug":"canada-real","asentamiento":"Fraccionamiento","cp":"45429","estado":"Jalisco","estado-slug":"jalisco","url":"https:\/\/cp.guiapaqueteria.com\/codigos-postales\/jalisco\/canada-real\/"},{"colonia":"Cañon","col-slug":"canon","asentamiento":"Colonia","cp":"45400","estado":"Jalisco","estado-slug":"jalisco","url":"https:\/\/cp.guiapaqueteria.com\/codigos-postales\/jalisco\/canon\/"},{"colonia":"Cerrito de La Reyna","col-slug":"cerrito-de-la-reyna","asentamiento":"Colonia","cp":"45410","estado":"Jalisco","estado-slug":"jalisco","url":"https:\/\/cp.guiapaqueteria.com\/codigos-postales\/jalisco\/cerrito-de-la-reyna\/"},{"colonia":"Cihualpilli","col-slug":"cihualpilli","asentamiento":"Colonia","cp":"45400","estado":"Jalisco","estado-slug":"jalisco","url":"https:\/\/cp.guiapaqueteria.com\/codigos-postales\/jalisco\/cihualpilli\/"},{"colonia":"Cipreses","col-slug":"cipreses","asentamiento":"Fraccionamiento","cp":"45403","estado":"Jalisco","estado-slug":"jalisco","url":"https:\/\/cp.guiapaqueteria.com\/codigos-postales\/jalisco\/cipreses\/"},{"colonia":"Ciudad Aztlán","col-slug":"ciudad-aztlan","asentamiento":"Colonia","cp":"45402","estado":"Jalisco","estado-slug":"jalisco","url":"https:\/\/cp.guiapaqueteria.com\/codigos-postales\/jalisco\/ciudad-aztlan\/"},{"colonia":"Colimilla","col-slug":"colimilla","asentamiento":"Colonia","cp":"45412","estado":"Jalisco","estado-slug":"jalisco","url":"https:\/\/cp.guiapaqueteria.com\/codigos-postales\/jalisco\/colimilla\/"},{"colonia":"Colinas de Altamira","col-slug":"colinas-de-altamira","asentamiento":"Fraccionamiento","cp":"45400","estado":"Jalisco","estado-slug":"jalisco","url":"https:\/\/cp.guiapaqueteria.com\/codigos-postales\/jalisco\/colinas-de-altamira\/"},{"colonia":"Colinas de La Cruz","col-slug":"colinas-de-la-cruz","asentamiento":"Colonia","cp":"45403","estado":"Jalisco","estado-slug":"jalisco","url":"https:\/\/cp.guiapaqueteria.com\/codigos-postales\/jalisco\/colinas-de-la-cruz\/"},{"colonia":"Colinas de San Carlos","col-slug":"colinas-de-san-carlos","asentamiento":"Colonia","cp":"45400","estado":"Jalisco","estado-slug":"jalisco","url":"https:\/\/cp.guiapaqueteria.com\/codigos-postales\/jalisco\/colinas-de-san-carlos\/"},{"colonia":"Colinas de Tonalá","col-slug":"colinas-de-tonala","asentamiento":"Colonia","cp":"45402","estado":"Jalisco","estado-slug":"jalisco","url":"https:\/\/cp.guiapaqueteria.com\/codigos-postales\/jalisco\/colinas-de-tonala\/"},{"colonia":"Colinas de Tonalá","col-slug":"colinas-de-tonala","asentamiento":"Fraccionamiento","cp":"45422","estado":"Jalisco","estado-slug":"jalisco","url":"https:\/\/cp.guiapaqueteria.com\/codigos-postales\/jalisco\/colinas-de-tonala\/"},{"colonia":"Colinas Santa Cruz II","col-slug":"colinas-santa-cruz-ii","asentamiento":"Colonia","cp":"45403","estado":"Jalisco","estado-slug":"jalisco","url":"https:\/\/cp.guiapaqueteria.com\/codigos-postales\/jalisco\/colinas-santa-cruz-ii\/"},{"colonia":"Colonia del Sur","col-slug":"colonia-del-sur","asentamiento":"Colonia","cp":"45400","estado":"Jalisco","estado-slug":"jalisco","url":"https:\/\/cp.guiapaqueteria.com\/codigos-postales\/jalisco\/colonia-del-sur\/"},{"colonia":"Colonos Ciudad Aztlán","col-slug":"colonos-ciudad-aztlan","asentamiento":"Colonia","cp":"45402","estado":"Jalisco","estado-slug":"jalisco","url":"https:\/\/cp.guiapaqueteria.com\/codigos-postales\/jalisco\/colonos-ciudad-aztlan\/"},{"colonia":"Colorines","col-slug":"colorines","asentamiento":"Colonia","cp":"45400","estado":"Jalisco","estado-slug":"jalisco","url":"https:\/\/cp.guiapaqueteria.com\/codigos-postales\/jalisco\/colorines\/"},{"colonia":"Colosio","col-slug":"colosio","asentamiento":"Colonia","cp":"45413","estado":"Jalisco","estado-slug":"jalisco","url":"https:\/\/cp.guiapaqueteria.com\/codigos-postales\/jalisco\/colosio\/"},{"colonia":"Comolca","col-slug":"comolca","asentamiento":"Colonia","cp":"45400","estado":"Jalisco","estado-slug":"jalisco","url":"https:\/\/cp.guiapaqueteria.com\/codigos-postales\/jalisco\/comolca\/"},{"colonia":"Concha","col-slug":"concha","asentamiento":"Fraccionamiento","cp":"45400","estado":"Jalisco","estado-slug":"jalisco","url":"https:\/\/cp.guiapaqueteria.com\/codigos-postales\/jalisco\/concha\/"},{"colonia":"Constancio Hernández Alvirde","col-slug":"constancio-hernandez-alvirde","asentamiento":"Fraccionamiento","cp":"45405","estado":"Jalisco","estado-slug":"jalisco","url":"https:\/\/cp.guiapaqueteria.com\/codigos-postales\/jalisco\/constancio-hernandez-alvirde\/"},{"colonia":"Coyula","col-slug":"coyula","asentamiento":"Colonia","cp":"45410","estado":"Jalisco","estado-slug":"jalisco","url":"https:\/\/cp.guiapaqueteria.com\/codigos-postales\/jalisco\/coyula\/"},{"colonia":"Cruz Loma","col-slug":"cruz-loma","asentamiento":"Colonia","cp":"45410","estado":"Jalisco","estado-slug":"jalisco","url":"https:\/\/cp.guiapaqueteria.com\/codigos-postales\/jalisco\/cruz-loma\/"},{"colonia":"Cuchara","col-slug":"cuchara","asentamiento":"Colonia","cp":"45400","estado":"Jalisco","estado-slug":"jalisco","url":"https:\/\/cp.guiapaqueteria.com\/codigos-postales\/jalisco\/cuchara\/"},{"colonia":"Del Laurel","col-slug":"del-laurel","asentamiento":"Colonia","cp":"45407","estado":"Jalisco","estado-slug":"jalisco","url":"https:\/\/cp.guiapaqueteria.com\/codigos-postales\/jalisco\/del-laurel\/"},{"colonia":"Del Valle","col-slug":"del-valle","asentamiento":"Colonia","cp":"45403","estado":"Jalisco","estado-slug":"jalisco","url":"https:\/\/cp.guiapaqueteria.com\/codigos-postales\/jalisco\/del-valle\/"},{"colonia":"Despertares","col-slug":"despertares","asentamiento":"Fraccionamiento","cp":"45410","estado":"Jalisco","estado-slug":"jalisco","url":"https:\/\/cp.guiapaqueteria.com\/codigos-postales\/jalisco\/despertares\/"},{"colonia":"Duque","col-slug":"duque","asentamiento":"Colonia","cp":"45410","estado":"Jalisco","estado-slug":"jalisco","url":"https:\/\/cp.guiapaqueteria.com\/codigos-postales\/jalisco\/duque\/"},{"colonia":"Educadores Jaliscienses","col-slug":"educadores-jaliscienses","asentamiento":"Colonia","cp":"45404","estado":"Jalisco","estado-slug":"jalisco","url":"https:\/\/cp.guiapaqueteria.com\/codigos-postales\/jalisco\/educadores-jaliscienses\/"},{"colonia":"Ejidal del Sol","col-slug":"ejidal-del-sol","asentamiento":"Fraccionamiento","cp":"45427","estado":"Jalisco","estado-slug":"jalisco","url":"https:\/\/cp.guiapaqueteria.com\/codigos-postales\/jalisco\/ejidal-del-sol\/"},{"colonia":"El Ahuatan","col-slug":"el-ahuatan","asentamiento":"Colonia","cp":"45412","estado":"Jalisco","estado-slug":"jalisco","url":"https:\/\/cp.guiapaqueteria.com\/codigos-postales\/jalisco\/el-ahuatan\/"},{"colonia":"El Amial","col-slug":"el-amial","asentamiento":"Colonia","cp":"45400","estado":"Jalisco","estado-slug":"jalisco","url":"https:\/\/cp.guiapaqueteria.com\/codigos-postales\/jalisco\/el-amial\/"},{"colonia":"El Arenal","col-slug":"el-arenal","asentamiento":"Colonia","cp":"45422","estado":"Jalisco","estado-slug":"jalisco","url":"https:\/\/cp.guiapaqueteria.com\/codigos-postales\/jalisco\/el-arenal\/"},{"colonia":"El Bajío de Santa Cruz","col-slug":"el-bajio-de-santa-cruz","asentamiento":"Colonia","cp":"45403","estado":"Jalisco","estado-slug":"jalisco","url":"https:\/\/cp.guiapaqueteria.com\/codigos-postales\/jalisco\/el-bajio-de-santa-cruz\/"},{"colonia":"El Barro","col-slug":"el-barro","asentamiento":"Unidad habitacional","cp":"45402","estado":"Jalisco","estado-slug":"jalisco","url":"https:\/\/cp.guiapaqueteria.com\/codigos-postales\/jalisco\/el-barro\/"},{"colonia":"El Bordo","col-slug":"el-bordo","asentamiento":"Colonia","cp":"45420","estado":"Jalisco","estado-slug":"jalisco","url":"https:\/\/cp.guiapaqueteria.com\/codigos-postales\/jalisco\/el-bordo\/"},{"colonia":"El Caracol","col-slug":"el-caracol","asentamiento":"Colonia","cp":"45407","estado":"Jalisco","estado-slug":"jalisco","url":"https:\/\/cp.guiapaqueteria.com\/codigos-postales\/jalisco\/el-caracol\/"},{"colonia":"El Cerrito","col-slug":"el-cerrito","asentamiento":"Colonia","cp":"45402","estado":"Jalisco","estado-slug":"jalisco","url":"https:\/\/cp.guiapaqueteria.com\/codigos-postales\/jalisco\/el-cerrito\/"},{"colonia":"El Cerro","col-slug":"el-cerro","asentamiento":"Unidad habitacional","cp":"45402","estado":"Jalisco","estado-slug":"jalisco","url":"https:\/\/cp.guiapaqueteria.com\/codigos-postales\/jalisco\/el-cerro\/"},{"colonia":"El Doradito","col-slug":"el-doradito","asentamiento":"Fraccionamiento","cp":"45403","estado":"Jalisco","estado-slug":"jalisco","url":"https:\/\/cp.guiapaqueteria.com\/codigos-postales\/jalisco\/el-doradito\/"},{"colonia":"El Gallo Colorado","col-slug":"el-gallo-colorado","asentamiento":"Colonia","cp":"45422","estado":"Jalisco","estado-slug":"jalisco","url":"https:\/\/cp.guiapaqueteria.com\/codigos-postales\/jalisco\/el-gallo-colorado\/"},{"colonia":"El Jordan","col-slug":"el-jordan","asentamiento":"Fraccionamiento","cp":"45427","estado":"Jalisco","estado-slug":"jalisco","url":"https:\/\/cp.guiapaqueteria.com\/codigos-postales\/jalisco\/el-jordan\/"},{"colonia":"El Mirador","col-slug":"el-mirador","asentamiento":"Colonia","cp":"45400","estado":"Jalisco","estado-slug":"jalisco","url":"https:\/\/cp.guiapaqueteria.com\/codigos-postales\/jalisco\/el-mirador\/"},{"colonia":"El Molino","col-slug":"el-molino","asentamiento":"Colonia","cp":"45407","estado":"Jalisco","estado-slug":"jalisco","url":"https:\/\/cp.guiapaqueteria.com\/codigos-postales\/jalisco\/el-molino\/"},{"colonia":"El Moral","col-slug":"el-moral","asentamiento":"Colonia","cp":"45417","estado":"Jalisco","estado-slug":"jalisco","url":"https:\/\/cp.guiapaqueteria.com\/codigos-postales\/jalisco\/el-moral\/"},{"colonia":"El Panorámico","col-slug":"el-panoramico","asentamiento":"Fraccionamiento","cp":"45410","estado":"Jalisco","estado-slug":"jalisco","url":"https:\/\/cp.guiapaqueteria.com\/codigos-postales\/jalisco\/el-panoramico\/"},{"colonia":"El Recodo","col-slug":"el-recodo","asentamiento":"Colonia","cp":"45400","estado":"Jalisco","estado-slug":"jalisco","url":"https:\/\/cp.guiapaqueteria.com\/codigos-postales\/jalisco\/el-recodo\/"},{"colonia":"El Remolino","col-slug":"el-remolino","asentamiento":"Fraccionamiento","cp":"45400","estado":"Jalisco","estado-slug":"jalisco","url":"https:\/\/cp.guiapaqueteria.com\/codigos-postales\/jalisco\/el-remolino\/"},{"colonia":"El Rincón","col-slug":"el-rincon","asentamiento":"Colonia","cp":"45420","estado":"Jalisco","estado-slug":"jalisco","url":"https:\/\/cp.guiapaqueteria.com\/codigos-postales\/jalisco\/el-rincon\/"},{"colonia":"El Rosario","col-slug":"el-rosario","asentamiento":"Colonia","cp":"45404","estado":"Jalisco","estado-slug":"jalisco","url":"https:\/\/cp.guiapaqueteria.com\/codigos-postales\/jalisco\/el-rosario\/"},{"colonia":"El Rosarito","col-slug":"el-rosarito","asentamiento":"Fraccionamiento","cp":"45404","estado":"Jalisco","estado-slug":"jalisco","url":"https:\/\/cp.guiapaqueteria.com\/codigos-postales\/jalisco\/el-rosarito\/"},{"colonia":"El Vado","col-slug":"el-vado","asentamiento":"Ranchería","cp":"45429","estado":"Jalisco","estado-slug":"jalisco","url":"https:\/\/cp.guiapaqueteria.com\/codigos-postales\/jalisco\/el-vado\/"},{"colonia":"El Zapote","col-slug":"el-zapote","asentamiento":"Colonia","cp":"45400","estado":"Jalisco","estado-slug":"jalisco","url":"https:\/\/cp.guiapaqueteria.com\/codigos-postales\/jalisco\/el-zapote\/"},{"colonia":"Emiliano Zapata","col-slug":"emiliano-zapata","asentamiento":"Colonia","cp":"45412","estado":"Jalisco","estado-slug":"jalisco","url":"https:\/\/cp.guiapaqueteria.com\/codigos-postales\/jalisco\/emiliano-zapata\/"},{"colonia":"Fidel Velázquez","col-slug":"fidel-velazquez","asentamiento":"Colonia","cp":"45400","estado":"Jalisco","estado-slug":"jalisco","url":"https:\/\/cp.guiapaqueteria.com\/codigos-postales\/jalisco\/fidel-velazquez\/"},{"colonia":"Flores Magón I Fracc","col-slug":"flores-magon-i-fracc","asentamiento":"Fraccionamiento","cp":"45403","estado":"Jalisco","estado-slug":"jalisco","url":"https:\/\/cp.guiapaqueteria.com\/codigos-postales\/jalisco\/flores-magon-i-fracc\/"},{"colonia":"Flores Magón II","col-slug":"flores-magon-ii","asentamiento":"Colonia","cp":"45403","estado":"Jalisco","estado-slug":"jalisco","url":"https:\/\/cp.guiapaqueteria.com\/codigos-postales\/jalisco\/flores-magon-ii\/"},{"colonia":"Francisco Villa","col-slug":"francisco-villa","asentamiento":"Colonia","cp":"45402","estado":"Jalisco","estado-slug":"jalisco","url":"https:\/\/cp.guiapaqueteria.com\/codigos-postales\/jalisco\/francisco-villa\/"},{"colonia":"Francisco Villa","col-slug":"francisco-villa","asentamiento":"Colonia","cp":"45412","estado":"Jalisco","estado-slug":"jalisco","url":"https:\/\/cp.guiapaqueteria.com\/codigos-postales\/jalisco\/francisco-villa\/"},{"colonia":"Fuentes Del Nilo","col-slug":"fuentes-del-nilo","asentamiento":"Fraccionamiento","cp":"45402","estado":"Jalisco","estado-slug":"jalisco","url":"https:\/\/cp.guiapaqueteria.com\/codigos-postales\/jalisco\/fuentes-del-nilo\/"},{"colonia":"Gallos Viejos","col-slug":"gallos-viejos","asentamiento":"Colonia","cp":"45412","estado":"Jalisco","estado-slug":"jalisco","url":"https:\/\/cp.guiapaqueteria.com\/codigos-postales\/jalisco\/gallos-viejos\/"},{"colonia":"Gavilanes","col-slug":"gavilanes","asentamiento":"Colonia","cp":"45404","estado":"Jalisco","estado-slug":"jalisco","url":"https:\/\/cp.guiapaqueteria.com\/codigos-postales\/jalisco\/gavilanes\/"},{"colonia":"Geranios","col-slug":"geranios","asentamiento":"Colonia","cp":"45406","estado":"Jalisco","estado-slug":"jalisco","url":"https:\/\/cp.guiapaqueteria.com\/codigos-postales\/jalisco\/geranios\/"},{"colonia":"Girasoles","col-slug":"girasoles","asentamiento":"Fraccionamiento","cp":"45406","estado":"Jalisco","estado-slug":"jalisco","url":"https:\/\/cp.guiapaqueteria.com\/codigos-postales\/jalisco\/girasoles\/"},{"colonia":"Guadalupana","col-slug":"guadalupana","asentamiento":"Colonia","cp":"45425","estado":"Jalisco","estado-slug":"jalisco","url":"https:\/\/cp.guiapaqueteria.com\/codigos-postales\/jalisco\/guadalupana\/"},{"colonia":"Hacienda de la Loma","col-slug":"hacienda-de-la-loma","asentamiento":"Colonia","cp":"45417","estado":"Jalisco","estado-slug":"jalisco","url":"https:\/\/cp.guiapaqueteria.com\/codigos-postales\/jalisco\/hacienda-de-la-loma\/"},{"colonia":"Hacienda Del Real","col-slug":"hacienda-del-real","asentamiento":"Colonia","cp":"45428","estado":"Jalisco","estado-slug":"jalisco","url":"https:\/\/cp.guiapaqueteria.com\/codigos-postales\/jalisco\/hacienda-del-real\/"},{"colonia":"Hacienda San Francisco","col-slug":"hacienda-san-francisco","asentamiento":"Hacienda","cp":"45403","estado":"Jalisco","estado-slug":"jalisco","url":"https:\/\/cp.guiapaqueteria.com\/codigos-postales\/jalisco\/hacienda-san-francisco\/"},{"colonia":"Haciendas de la Reyna","col-slug":"haciendas-de-la-reyna","asentamiento":"Fraccionamiento","cp":"45410","estado":"Jalisco","estado-slug":"jalisco","url":"https:\/\/cp.guiapaqueteria.com\/codigos-postales\/jalisco\/haciendas-de-la-reyna\/"},{"colonia":"Haciendas de Tonalá","col-slug":"haciendas-de-tonala","asentamiento":"Colonia","cp":"45429","estado":"Jalisco","estado-slug":"jalisco","url":"https:\/\/cp.guiapaqueteria.com\/codigos-postales\/jalisco\/haciendas-de-tonala\/"},{"colonia":"Hidalgo de Tonala","col-slug":"hidalgo-de-tonala","asentamiento":"Colonia","cp":"45400","estado":"Jalisco","estado-slug":"jalisco","url":"https:\/\/cp.guiapaqueteria.com\/codigos-postales\/jalisco\/hidalgo-de-tonala\/"},{"colonia":"Hipódromo","col-slug":"hipodromo","asentamiento":"Colonia","cp":"45428","estado":"Jalisco","estado-slug":"jalisco","url":"https:\/\/cp.guiapaqueteria.com\/codigos-postales\/jalisco\/hipodromo\/"},{"colonia":"Huerta","col-slug":"huerta","asentamiento":"Fraccionamiento","cp":"45404","estado":"Jalisco","estado-slug":"jalisco","url":"https:\/\/cp.guiapaqueteria.com\/codigos-postales\/jalisco\/huerta\/"},{"colonia":"Huertas de San Gaspar","col-slug":"huertas-de-san-gaspar","asentamiento":"Colonia","cp":"45408","estado":"Jalisco","estado-slug":"jalisco","url":"https:\/\/cp.guiapaqueteria.com\/codigos-postales\/jalisco\/huertas-de-san-gaspar\/"},{"colonia":"Huertas del Valle","col-slug":"huertas-del-valle","asentamiento":"Fraccionamiento","cp":"45408","estado":"Jalisco","estado-slug":"jalisco","url":"https:\/\/cp.guiapaqueteria.com\/codigos-postales\/jalisco\/huertas-del-valle\/"},{"colonia":"Industrial Nueva Central Camionera","col-slug":"industrial-nueva-central-camionera","asentamiento":"Fraccionamiento","cp":"45402","estado":"Jalisco","estado-slug":"jalisco","url":"https:\/\/cp.guiapaqueteria.com\/codigos-postales\/jalisco\/industrial-nueva-central-camionera\/"},{"colonia":"INFONAVIT La Soledad","col-slug":"infonavit-la-soledad","asentamiento":"Unidad habitacional","cp":"45403","estado":"Jalisco","estado-slug":"jalisco","url":"https:\/\/cp.guiapaqueteria.com\/codigos-postales\/jalisco\/infonavit-la-soledad\/"},{"colonia":"INFONAVIT Río Nilo","col-slug":"infonavit-rio-nilo","asentamiento":"Unidad habitacional","cp":"45403","estado":"Jalisco","estado-slug":"jalisco","url":"https:\/\/cp.guiapaqueteria.com\/codigos-postales\/jalisco\/infonavit-rio-nilo\/"},{"colonia":"Jacarandas","col-slug":"jacarandas","asentamiento":"Fraccionamiento","cp":"45406","estado":"Jalisco","estado-slug":"jalisco","url":"https:\/\/cp.guiapaqueteria.com\/codigos-postales\/jalisco\/jacarandas\/"},{"colonia":"Jalisco 1a. Sección","col-slug":"jalisco-1a-seccion","asentamiento":"Colonia","cp":"45412","estado":"Jalisco","estado-slug":"jalisco","url":"https:\/\/cp.guiapaqueteria.com\/codigos-postales\/jalisco\/jalisco-1a-seccion\/"},{"colonia":"Jalisco 2a. Sección","col-slug":"jalisco-2a-seccion","asentamiento":"Colonia","cp":"45412","estado":"Jalisco","estado-slug":"jalisco","url":"https:\/\/cp.guiapaqueteria.com\/codigos-postales\/jalisco\/jalisco-2a-seccion\/"},{"colonia":"Jardines de Elizabeth","col-slug":"jardines-de-elizabeth","asentamiento":"Fraccionamiento","cp":"45404","estado":"Jalisco","estado-slug":"jalisco","url":"https:\/\/cp.guiapaqueteria.com\/codigos-postales\/jalisco\/jardines-de-elizabeth\/"},{"colonia":"Jardines de la Cañada","col-slug":"jardines-de-la-canada","asentamiento":"Fraccionamiento","cp":"45410","estado":"Jalisco","estado-slug":"jalisco","url":"https:\/\/cp.guiapaqueteria.com\/codigos-postales\/jalisco\/jardines-de-la-canada\/"},{"colonia":"Jardines de La Cruz Oriente","col-slug":"jardines-de-la-cruz-oriente","asentamiento":"Fraccionamiento","cp":"45417","estado":"Jalisco","estado-slug":"jalisco","url":"https:\/\/cp.guiapaqueteria.com\/codigos-postales\/jalisco\/jardines-de-la-cruz-oriente\/"},{"colonia":"Jardines de La Hacienda","col-slug":"jardines-de-la-hacienda","asentamiento":"Fraccionamiento","cp":"45428","estado":"Jalisco","estado-slug":"jalisco","url":"https:\/\/cp.guiapaqueteria.com\/codigos-postales\/jalisco\/jardines-de-la-hacienda\/"},{"colonia":"Jardines de La Reyna","col-slug":"jardines-de-la-reyna","asentamiento":"Fraccionamiento","cp":"45410","estado":"Jalisco","estado-slug":"jalisco","url":"https:\/\/cp.guiapaqueteria.com\/codigos-postales\/jalisco\/jardines-de-la-reyna\/"},{"colonia":"Jardines de San Rafael","col-slug":"jardines-de-san-rafael","asentamiento":"Fraccionamiento","cp":"45400","estado":"Jalisco","estado-slug":"jalisco","url":"https:\/\/cp.guiapaqueteria.com\/codigos-postales\/jalisco\/jardines-de-san-rafael\/"},{"colonia":"Jardines de Tonala","col-slug":"jardines-de-tonala","asentamiento":"Fraccionamiento","cp":"45400","estado":"Jalisco","estado-slug":"jalisco","url":"https:\/\/cp.guiapaqueteria.com\/codigos-postales\/jalisco\/jardines-de-tonala\/"},{"colonia":"Jardines Del Rosario","col-slug":"jardines-del-rosario","asentamiento":"Colonia","cp":"45404","estado":"Jalisco","estado-slug":"jalisco","url":"https:\/\/cp.guiapaqueteria.com\/codigos-postales\/jalisco\/jardines-del-rosario\/"},{"colonia":"Jardines Mirador","col-slug":"jardines-mirador","asentamiento":"Colonia","cp":"45428","estado":"Jalisco","estado-slug":"jalisco","url":"https:\/\/cp.guiapaqueteria.com\/codigos-postales\/jalisco\/jardines-mirador\/"},{"colonia":"Jauja","col-slug":"jauja","asentamiento":"Colonia","cp":"45428","estado":"Jalisco","estado-slug":"jalisco","url":"https:\/\/cp.guiapaqueteria.com\/codigos-postales\/jalisco\/jauja\/"},{"colonia":"Jazmín","col-slug":"jazmin","asentamiento":"Colonia","cp":"45408","estado":"Jalisco","estado-slug":"jalisco","url":"https:\/\/cp.guiapaqueteria.com\/codigos-postales\/jalisco\/jazmin\/"},{"colonia":"Juárez","col-slug":"juarez","asentamiento":"Colonia","cp":"45410","estado":"Jalisco","estado-slug":"jalisco","url":"https:\/\/cp.guiapaqueteria.com\/codigos-postales\/jalisco\/juarez\/"},{"colonia":"La Alberca","col-slug":"la-alberca","asentamiento":"Colonia","cp":"45400","estado":"Jalisco","estado-slug":"jalisco","url":"https:\/\/cp.guiapaqueteria.com\/codigos-postales\/jalisco\/la-alberca\/"},{"colonia":"La Arena","col-slug":"la-arena","asentamiento":"Colonia","cp":"45407","estado":"Jalisco","estado-slug":"jalisco","url":"https:\/\/cp.guiapaqueteria.com\/codigos-postales\/jalisco\/la-arena\/"},{"colonia":"La Cabaña","col-slug":"la-cabana","asentamiento":"Colonia","cp":"45400","estado":"Jalisco","estado-slug":"jalisco","url":"https:\/\/cp.guiapaqueteria.com\/codigos-postales\/jalisco\/la-cabana\/"},{"colonia":"La Calma","col-slug":"la-calma","asentamiento":"Colonia","cp":"45428","estado":"Jalisco","estado-slug":"jalisco","url":"https:\/\/cp.guiapaqueteria.com\/codigos-postales\/jalisco\/la-calma\/"},{"colonia":"La Cañada","col-slug":"la-canada","asentamiento":"Colonia","cp":"45408","estado":"Jalisco","estado-slug":"jalisco","url":"https:\/\/cp.guiapaqueteria.com\/codigos-postales\/jalisco\/la-canada\/"},{"colonia":"La Comolea","col-slug":"la-comolea","asentamiento":"Colonia","cp":"45400","estado":"Jalisco","estado-slug":"jalisco","url":"https:\/\/cp.guiapaqueteria.com\/codigos-postales\/jalisco\/la-comolea\/"},{"colonia":"La Cruz","col-slug":"la-cruz","asentamiento":"Colonia","cp":"45407","estado":"Jalisco","estado-slug":"jalisco","url":"https:\/\/cp.guiapaqueteria.com\/codigos-postales\/jalisco\/la-cruz\/"},{"colonia":"La Esperanza","col-slug":"la-esperanza","asentamiento":"Colonia","cp":"45428","estado":"Jalisco","estado-slug":"jalisco","url":"https:\/\/cp.guiapaqueteria.com\/codigos-postales\/jalisco\/la-esperanza\/"},{"colonia":"La Gigantera","col-slug":"la-gigantera","asentamiento":"Colonia","cp":"45420","estado":"Jalisco","estado-slug":"jalisco","url":"https:\/\/cp.guiapaqueteria.com\/codigos-postales\/jalisco\/la-gigantera\/"},{"colonia":"La Guadalupana","col-slug":"la-guadalupana","asentamiento":"Colonia","cp":"45400","estado":"Jalisco","estado-slug":"jalisco","url":"https:\/\/cp.guiapaqueteria.com\/codigos-postales\/jalisco\/la-guadalupana\/"},{"colonia":"La Hortaliza","col-slug":"la-hortaliza","asentamiento":"Colonia","cp":"45404","estado":"Jalisco","estado-slug":"jalisco","url":"https:\/\/cp.guiapaqueteria.com\/codigos-postales\/jalisco\/la-hortaliza\/"},{"colonia":"La Ladrillera","col-slug":"la-ladrillera","asentamiento":"Colonia","cp":"45428","estado":"Jalisco","estado-slug":"jalisco","url":"https:\/\/cp.guiapaqueteria.com\/codigos-postales\/jalisco\/la-ladrillera\/"},{"colonia":"La Liga","col-slug":"la-liga","asentamiento":"Colonia","cp":"45420","estado":"Jalisco","estado-slug":"jalisco","url":"https:\/\/cp.guiapaqueteria.com\/codigos-postales\/jalisco\/la-liga\/"},{"colonia":"La Llave","col-slug":"la-llave","asentamiento":"Fraccionamiento","cp":"45428","estado":"Jalisco","estado-slug":"jalisco","url":"https:\/\/cp.guiapaqueteria.com\/codigos-postales\/jalisco\/la-llave\/"},{"colonia":"La Loma","col-slug":"la-loma","asentamiento":"Colonia","cp":"45422","estado":"Jalisco","estado-slug":"jalisco","url":"https:\/\/cp.guiapaqueteria.com\/codigos-postales\/jalisco\/la-loma\/"},{"colonia":"La Mesa I","col-slug":"la-mesa-i","asentamiento":"Colonia","cp":"45400","estado":"Jalisco","estado-slug":"jalisco","url":"https:\/\/cp.guiapaqueteria.com\/codigos-postales\/jalisco\/la-mesa-i\/"},{"colonia":"La Mesa II","col-slug":"la-mesa-ii","asentamiento":"Colonia","cp":"45400","estado":"Jalisco","estado-slug":"jalisco","url":"https:\/\/cp.guiapaqueteria.com\/codigos-postales\/jalisco\/la-mesa-ii\/"},{"colonia":"La Mojonera","col-slug":"la-mojonera","asentamiento":"Colonia","cp":"45408","estado":"Jalisco","estado-slug":"jalisco","url":"https:\/\/cp.guiapaqueteria.com\/codigos-postales\/jalisco\/la-mojonera\/"},{"colonia":"La Noria","col-slug":"la-noria","asentamiento":"Fraccionamiento","cp":"45412","estado":"Jalisco","estado-slug":"jalisco","url":"https:\/\/cp.guiapaqueteria.com\/codigos-postales\/jalisco\/la-noria\/"},{"colonia":"La Perseverancia","col-slug":"la-perseverancia","asentamiento":"Fraccionamiento","cp":"45408","estado":"Jalisco","estado-slug":"jalisco","url":"https:\/\/cp.guiapaqueteria.com\/codigos-postales\/jalisco\/la-perseverancia\/"},{"colonia":"La Pila","col-slug":"la-pila","asentamiento":"Colonia","cp":"45405","estado":"Jalisco","estado-slug":"jalisco","url":"https:\/\/cp.guiapaqueteria.com\/codigos-postales\/jalisco\/la-pila\/"},{"colonia":"La Pila de San Gaspar","col-slug":"la-pila-de-san-gaspar","asentamiento":"Colonia","cp":"45408","estado":"Jalisco","estado-slug":"jalisco","url":"https:\/\/cp.guiapaqueteria.com\/codigos-postales\/jalisco\/la-pila-de-san-gaspar\/"},{"colonia":"La Pilita","col-slug":"la-pilita","asentamiento":"Colonia","cp":"45420","estado":"Jalisco","estado-slug":"jalisco","url":"https:\/\/cp.guiapaqueteria.com\/codigos-postales\/jalisco\/la-pilita\/"},{"colonia":"La Presa","col-slug":"la-presa","asentamiento":"Colonia","cp":"45412","estado":"Jalisco","estado-slug":"jalisco","url":"https:\/\/cp.guiapaqueteria.com\/codigos-postales\/jalisco\/la-presa\/"},{"colonia":"La Providencia","col-slug":"la-providencia","asentamiento":"Fraccionamiento","cp":"45400","estado":"Jalisco","estado-slug":"jalisco","url":"https:\/\/cp.guiapaqueteria.com\/codigos-postales\/jalisco\/la-providencia\/"},{"colonia":"La Puerta","col-slug":"la-puerta","asentamiento":"Colonia","cp":"45420","estado":"Jalisco","estado-slug":"jalisco","url":"https:\/\/cp.guiapaqueteria.com\/codigos-postales\/jalisco\/la-puerta\/"},{"colonia":"La Resolana","col-slug":"la-resolana","asentamiento":"Colonia","cp":"45412","estado":"Jalisco","estado-slug":"jalisco","url":"https:\/\/cp.guiapaqueteria.com\/codigos-postales\/jalisco\/la-resolana\/"},{"colonia":"La Severiana","col-slug":"la-severiana","asentamiento":"Colonia","cp":"45420","estado":"Jalisco","estado-slug":"jalisco","url":"https:\/\/cp.guiapaqueteria.com\/codigos-postales\/jalisco\/la-severiana\/"},{"colonia":"La Villa","col-slug":"la-villa","asentamiento":"Colonia","cp":"45407","estado":"Jalisco","estado-slug":"jalisco","url":"https:\/\/cp.guiapaqueteria.com\/codigos-postales\/jalisco\/la-villa\/"},{"colonia":"Ladera","col-slug":"ladera","asentamiento":"Colonia","cp":"45402","estado":"Jalisco","estado-slug":"jalisco","url":"https:\/\/cp.guiapaqueteria.com\/codigos-postales\/jalisco\/ladera\/"},{"colonia":"Larguero","col-slug":"larguero","asentamiento":"Colonia","cp":"45402","estado":"Jalisco","estado-slug":"jalisco","url":"https:\/\/cp.guiapaqueteria.com\/codigos-postales\/jalisco\/larguero\/"},{"colonia":"Las Cañadas","col-slug":"las-canadas","asentamiento":"Fraccionamiento","cp":"45418","estado":"Jalisco","estado-slug":"jalisco","url":"https:\/\/cp.guiapaqueteria.com\/codigos-postales\/jalisco\/las-canadas\/"},{"colonia":"Las Gabrielas","col-slug":"las-gabrielas","asentamiento":"Fraccionamiento","cp":"45400","estado":"Jalisco","estado-slug":"jalisco","url":"https:\/\/cp.guiapaqueteria.com\/codigos-postales\/jalisco\/las-gabrielas\/"},{"colonia":"Las Torres","col-slug":"las-torres","asentamiento":"Colonia","cp":"45405","estado":"Jalisco","estado-slug":"jalisco","url":"https:\/\/cp.guiapaqueteria.com\/codigos-postales\/jalisco\/las-torres\/"},{"colonia":"Lázaro Cárdenas","col-slug":"lazaro-cardenas","asentamiento":"Colonia","cp":"45413","estado":"Jalisco","estado-slug":"jalisco","url":"https:\/\/cp.guiapaqueteria.com\/codigos-postales\/jalisco\/lazaro-cardenas\/"},{"colonia":"Lázaro Cárdenas (Barranquitas)","col-slug":"lazaro-cardenas-barranquitas","asentamiento":"Colonia","cp":"45412","estado":"Jalisco","estado-slug":"jalisco","url":"https:\/\/cp.guiapaqueteria.com\/codigos-postales\/jalisco\/lazaro-cardenas-barranquitas\/"},{"colonia":"Leyes de Reforma","col-slug":"leyes-de-reforma","asentamiento":"Colonia","cp":"45404","estado":"Jalisco","estado-slug":"jalisco","url":"https:\/\/cp.guiapaqueteria.com\/codigos-postales\/jalisco\/leyes-de-reforma\/"},{"colonia":"Linda Vista","col-slug":"linda-vista","asentamiento":"Colonia","cp":"45402","estado":"Jalisco","estado-slug":"jalisco","url":"https:\/\/cp.guiapaqueteria.com\/codigos-postales\/jalisco\/linda-vista\/"},{"colonia":"Loma Bonita 1a Sección","col-slug":"loma-bonita-1a-seccion","asentamiento":"Colonia","cp":"45405","estado":"Jalisco","estado-slug":"jalisco","url":"https:\/\/cp.guiapaqueteria.com\/codigos-postales\/jalisco\/loma-bonita-1a-seccion\/"},{"colonia":"Loma Bonita 2a Sección","col-slug":"loma-bonita-2a-seccion","asentamiento":"Colonia","cp":"45405","estado":"Jalisco","estado-slug":"jalisco","url":"https:\/\/cp.guiapaqueteria.com\/codigos-postales\/jalisco\/loma-bonita-2a-seccion\/"},{"colonia":"Loma Bonita 3a Sección","col-slug":"loma-bonita-3a-seccion","asentamiento":"Colonia","cp":"45405","estado":"Jalisco","estado-slug":"jalisco","url":"https:\/\/cp.guiapaqueteria.com\/codigos-postales\/jalisco\/loma-bonita-3a-seccion\/"},{"colonia":"Loma de San Gaspar","col-slug":"loma-de-san-gaspar","asentamiento":"Colonia","cp":"45412","estado":"Jalisco","estado-slug":"jalisco","url":"https:\/\/cp.guiapaqueteria.com\/codigos-postales\/jalisco\/loma-de-san-gaspar\/"},{"colonia":"Loma Dorada","col-slug":"loma-dorada","asentamiento":"Fraccionamiento","cp":"45402","estado":"Jalisco","estado-slug":"jalisco","url":"https:\/\/cp.guiapaqueteria.com\/codigos-postales\/jalisco\/loma-dorada\/"},{"colonia":"Loma Dorada Ejidal","col-slug":"loma-dorada-ejidal","asentamiento":"Fraccionamiento","cp":"45402","estado":"Jalisco","estado-slug":"jalisco","url":"https:\/\/cp.guiapaqueteria.com\/codigos-postales\/jalisco\/loma-dorada-ejidal\/"},{"colonia":"Loma Linda","col-slug":"loma-linda","asentamiento":"Fraccionamiento","cp":"45410","estado":"Jalisco","estado-slug":"jalisco","url":"https:\/\/cp.guiapaqueteria.com\/codigos-postales\/jalisco\/loma-linda\/"},{"colonia":"Loma Sur","col-slug":"loma-sur","asentamiento":"Fraccionamiento","cp":"45400","estado":"Jalisco","estado-slug":"jalisco","url":"https:\/\/cp.guiapaqueteria.com\/codigos-postales\/jalisco\/loma-sur\/"},{"colonia":"Lomas de Aztlán","col-slug":"lomas-de-aztlan","asentamiento":"Fraccionamiento","cp":"45402","estado":"Jalisco","estado-slug":"jalisco","url":"https:\/\/cp.guiapaqueteria.com\/codigos-postales\/jalisco\/lomas-de-aztlan\/"},{"colonia":"Lomas de La Soledad","col-slug":"lomas-de-la-soledad","asentamiento":"Colonia","cp":"45403","estado":"Jalisco","estado-slug":"jalisco","url":"https:\/\/cp.guiapaqueteria.com\/codigos-postales\/jalisco\/lomas-de-la-soledad\/"},{"colonia":"Lomas de los Pájaros","col-slug":"lomas-de-los-pajaros","asentamiento":"Colonia","cp":"45403","estado":"Jalisco","estado-slug":"jalisco","url":"https:\/\/cp.guiapaqueteria.com\/codigos-postales\/jalisco\/lomas-de-los-pajaros\/"},{"colonia":"Lomas de San Miguel","col-slug":"lomas-de-san-miguel","asentamiento":"Fraccionamiento","cp":"45425","estado":"Jalisco","estado-slug":"jalisco","url":"https:\/\/cp.guiapaqueteria.com\/codigos-postales\/jalisco\/lomas-de-san-miguel\/"},{"colonia":"Lomas de San Miguel III","col-slug":"lomas-de-san-miguel-iii","asentamiento":"Fraccionamiento","cp":"45425","estado":"Jalisco","estado-slug":"jalisco","url":"https:\/\/cp.guiapaqueteria.com\/codigos-postales\/jalisco\/lomas-de-san-miguel-iii\/"},{"colonia":"Lomas de Tonalá","col-slug":"lomas-de-tonala","asentamiento":"Colonia","cp":"45400","estado":"Jalisco","estado-slug":"jalisco","url":"https:\/\/cp.guiapaqueteria.com\/codigos-postales\/jalisco\/lomas-de-tonala\/"},{"colonia":"Lomas de Zalatitan","col-slug":"lomas-de-zalatitan","asentamiento":"Colonia","cp":"45407","estado":"Jalisco","estado-slug":"jalisco","url":"https:\/\/cp.guiapaqueteria.com\/codigos-postales\/jalisco\/lomas-de-zalatitan\/"},{"colonia":"Lomas del Camichin","col-slug":"lomas-del-camichin","asentamiento":"Colonia","cp":"45403","estado":"Jalisco","estado-slug":"jalisco","url":"https:\/\/cp.guiapaqueteria.com\/codigos-postales\/jalisco\/lomas-del-camichin\/"},{"colonia":"Lomas Del Laurel","col-slug":"lomas-del-laurel","asentamiento":"Colonia","cp":"45407","estado":"Jalisco","estado-slug":"jalisco","url":"https:\/\/cp.guiapaqueteria.com\/codigos-postales\/jalisco\/lomas-del-laurel\/"},{"colonia":"Lomas Del Manantial","col-slug":"lomas-del-manantial","asentamiento":"Colonia","cp":"45402","estado":"Jalisco","estado-slug":"jalisco","url":"https:\/\/cp.guiapaqueteria.com\/codigos-postales\/jalisco\/lomas-del-manantial\/"},{"colonia":"Lomas Del Manantial","col-slug":"lomas-del-manantial","asentamiento":"Colonia","cp":"45405","estado":"Jalisco","estado-slug":"jalisco","url":"https:\/\/cp.guiapaqueteria.com\/codigos-postales\/jalisco\/lomas-del-manantial\/"},{"colonia":"Lomas Gaspar","col-slug":"lomas-gaspar","asentamiento":"Colonia","cp":"45408","estado":"Jalisco","estado-slug":"jalisco","url":"https:\/\/cp.guiapaqueteria.com\/codigos-postales\/jalisco\/lomas-gaspar\/"},{"colonia":"López Cotilla","col-slug":"lopez-cotilla","asentamiento":"Fraccionamiento","cp":"45408","estado":"Jalisco","estado-slug":"jalisco","url":"https:\/\/cp.guiapaqueteria.com\/codigos-postales\/jalisco\/lopez-cotilla\/"},{"colonia":"Los Amiales","col-slug":"los-amiales","asentamiento":"Colonia","cp":"45422","estado":"Jalisco","estado-slug":"jalisco","url":"https:\/\/cp.guiapaqueteria.com\/codigos-postales\/jalisco\/los-amiales\/"},{"colonia":"Los Camichines","col-slug":"los-camichines","asentamiento":"Colonia","cp":"45407","estado":"Jalisco","estado-slug":"jalisco","url":"https:\/\/cp.guiapaqueteria.com\/codigos-postales\/jalisco\/los-camichines\/"},{"colonia":"Los Camichines 2","col-slug":"los-camichines-2","asentamiento":"Colonia","cp":"45407","estado":"Jalisco","estado-slug":"jalisco","url":"https:\/\/cp.guiapaqueteria.com\/codigos-postales\/jalisco\/los-camichines-2\/"},{"colonia":"Los Camichines 3","col-slug":"los-camichines-3","asentamiento":"Colonia","cp":"45407","estado":"Jalisco","estado-slug":"jalisco","url":"https:\/\/cp.guiapaqueteria.com\/codigos-postales\/jalisco\/los-camichines-3\/"},{"colonia":"Los Camichines I","col-slug":"los-camichines-i","asentamiento":"Colonia","cp":"45403","estado":"Jalisco","estado-slug":"jalisco","url":"https:\/\/cp.guiapaqueteria.com\/codigos-postales\/jalisco\/los-camichines-i\/"},{"colonia":"Los Camichines II","col-slug":"los-camichines-ii","asentamiento":"Fraccionamiento","cp":"45403","estado":"Jalisco","estado-slug":"jalisco","url":"https:\/\/cp.guiapaqueteria.com\/codigos-postales\/jalisco\/los-camichines-ii\/"},{"colonia":"Los Conejos","col-slug":"los-conejos","asentamiento":"Fraccionamiento","cp":"45412","estado":"Jalisco","estado-slug":"jalisco","url":"https:\/\/cp.guiapaqueteria.com\/codigos-postales\/jalisco\/los-conejos\/"},{"colonia":"Los Cuadros","col-slug":"los-cuadros","asentamiento":"Colonia","cp":"45402","estado":"Jalisco","estado-slug":"jalisco","url":"https:\/\/cp.guiapaqueteria.com\/codigos-postales\/jalisco\/los-cuadros\/"},{"colonia":"Los Encinos","col-slug":"los-encinos","asentamiento":"Colonia","cp":"45422","estado":"Jalisco","estado-slug":"jalisco","url":"https:\/\/cp.guiapaqueteria.com\/codigos-postales\/jalisco\/los-encinos\/"},{"colonia":"Los Liberales","col-slug":"los-liberales","asentamiento":"Colonia","cp":"45402","estado":"Jalisco","estado-slug":"jalisco","url":"https:\/\/cp.guiapaqueteria.com\/codigos-postales\/jalisco\/los-liberales\/"},{"colonia":"Los Manantiales","col-slug":"los-manantiales","asentamiento":"Colonia","cp":"45407","estado":"Jalisco","estado-slug":"jalisco","url":"https:\/\/cp.guiapaqueteria.com\/codigos-postales\/jalisco\/los-manantiales\/"},{"colonia":"Los Manguitos","col-slug":"los-manguitos","asentamiento":"Colonia","cp":"45405","estado":"Jalisco","estado-slug":"jalisco","url":"https:\/\/cp.guiapaqueteria.com\/codigos-postales\/jalisco\/los-manguitos\/"},{"colonia":"Los Músicos","col-slug":"los-musicos","asentamiento":"Colonia","cp":"45402","estado":"Jalisco","estado-slug":"jalisco","url":"https:\/\/cp.guiapaqueteria.com\/codigos-postales\/jalisco\/los-musicos\/"},{"colonia":"Los Pajaritos","col-slug":"los-pajaritos","asentamiento":"Colonia","cp":"45428","estado":"Jalisco","estado-slug":"jalisco","url":"https:\/\/cp.guiapaqueteria.com\/codigos-postales\/jalisco\/los-pajaritos\/"},{"colonia":"Los Pinos","col-slug":"los-pinos","asentamiento":"Fraccionamiento","cp":"45406","estado":"Jalisco","estado-slug":"jalisco","url":"https:\/\/cp.guiapaqueteria.com\/codigos-postales\/jalisco\/los-pinos\/"},{"colonia":"Los Pocitos","col-slug":"los-pocitos","asentamiento":"Colonia","cp":"45403","estado":"Jalisco","estado-slug":"jalisco","url":"https:\/\/cp.guiapaqueteria.com\/codigos-postales\/jalisco\/los-pocitos\/"},{"colonia":"Los Puestos","col-slug":"los-puestos","asentamiento":"Colonia","cp":"45420","estado":"Jalisco","estado-slug":"jalisco","url":"https:\/\/cp.guiapaqueteria.com\/codigos-postales\/jalisco\/los-puestos\/"},{"colonia":"Los Vizcarra (San Isidro)","col-slug":"los-vizcarra-san-isidro","asentamiento":"Colonia","cp":"45410","estado":"Jalisco","estado-slug":"jalisco","url":"https:\/\/cp.guiapaqueteria.com\/codigos-postales\/jalisco\/los-vizcarra-san-isidro\/"},{"colonia":"Luis Alonso González","col-slug":"luis-alonso-gonzalez","asentamiento":"Colonia","cp":"45428","estado":"Jalisco","estado-slug":"jalisco","url":"https:\/\/cp.guiapaqueteria.com\/codigos-postales\/jalisco\/luis-alonso-gonzalez\/"},{"colonia":"Maravillas","col-slug":"maravillas","asentamiento":"Colonia","cp":"45403","estado":"Jalisco","estado-slug":"jalisco","url":"https:\/\/cp.guiapaqueteria.com\/codigos-postales\/jalisco\/maravillas\/"},{"colonia":"Mesa de las Gamboas","col-slug":"mesa-de-las-gamboas","asentamiento":"Colonia","cp":"45410","estado":"Jalisco","estado-slug":"jalisco","url":"https:\/\/cp.guiapaqueteria.com\/codigos-postales\/jalisco\/mesa-de-las-gamboas\/"},{"colonia":"Mirador de La Reyna","col-slug":"mirador-de-la-reyna","asentamiento":"Colonia","cp":"45400","estado":"Jalisco","estado-slug":"jalisco","url":"https:\/\/cp.guiapaqueteria.com\/codigos-postales\/jalisco\/mirador-de-la-reyna\/"},{"colonia":"Mirador Del Sol","col-slug":"mirador-del-sol","asentamiento":"Colonia","cp":"45400","estado":"Jalisco","estado-slug":"jalisco","url":"https:\/\/cp.guiapaqueteria.com\/codigos-postales\/jalisco\/mirador-del-sol\/"},{"colonia":"Mirador Oriente","col-slug":"mirador-oriente","asentamiento":"Fraccionamiento","cp":"45412","estado":"Jalisco","estado-slug":"jalisco","url":"https:\/\/cp.guiapaqueteria.com\/codigos-postales\/jalisco\/mirador-oriente\/"},{"colonia":"Misión Acueducto","col-slug":"mision-acueducto","asentamiento":"Fraccionamiento","cp":"45410","estado":"Jalisco","estado-slug":"jalisco","url":"https:\/\/cp.guiapaqueteria.com\/codigos-postales\/jalisco\/mision-acueducto\/"},{"colonia":"Misión Cantera","col-slug":"mision-cantera","asentamiento":"Colonia","cp":"45404","estado":"Jalisco","estado-slug":"jalisco","url":"https:\/\/cp.guiapaqueteria.com\/codigos-postales\/jalisco\/mision-cantera\/"},{"colonia":"Misión de los Viñedos","col-slug":"mision-de-los-vinedos","asentamiento":"Fraccionamiento","cp":"45410","estado":"Jalisco","estado-slug":"jalisco","url":"https:\/\/cp.guiapaqueteria.com\/codigos-postales\/jalisco\/mision-de-los-vinedos\/"},{"colonia":"Misión de San Francisco","col-slug":"mision-de-san-francisco","asentamiento":"Fraccionamiento","cp":"45406","estado":"Jalisco","estado-slug":"jalisco","url":"https:\/\/cp.guiapaqueteria.com\/codigos-postales\/jalisco\/mision-de-san-francisco\/"},{"colonia":"Misión Del Campanario","col-slug":"mision-del-campanario","asentamiento":"Fraccionamiento","cp":"45400","estado":"Jalisco","estado-slug":"jalisco","url":"https:\/\/cp.guiapaqueteria.com\/codigos-postales\/jalisco\/mision-del-campanario\/"},{"colonia":"Nuevo Israel","col-slug":"nuevo-israel","asentamiento":"Colonia","cp":"45412","estado":"Jalisco","estado-slug":"jalisco","url":"https:\/\/cp.guiapaqueteria.com\/codigos-postales\/jalisco\/nuevo-israel\/"},{"colonia":"Nuevo Santa Cruz","col-slug":"nuevo-santa-cruz","asentamiento":"Barrio","cp":"45402","estado":"Jalisco","estado-slug":"jalisco","url":"https:\/\/cp.guiapaqueteria.com\/codigos-postales\/jalisco\/nuevo-santa-cruz\/"},{"colonia":"Ocotillo","col-slug":"ocotillo","asentamiento":"Colonia","cp":"45422","estado":"Jalisco","estado-slug":"jalisco","url":"https:\/\/cp.guiapaqueteria.com\/codigos-postales\/jalisco\/ocotillo\/"},{"colonia":"Ojo de Agua","col-slug":"ojo-de-agua","asentamiento":"Colonia","cp":"45420","estado":"Jalisco","estado-slug":"jalisco","url":"https:\/\/cp.guiapaqueteria.com\/codigos-postales\/jalisco\/ojo-de-agua\/"},{"colonia":"Pachaguillo","col-slug":"pachaguillo","asentamiento":"Colonia","cp":"45400","estado":"Jalisco","estado-slug":"jalisco","url":"https:\/\/cp.guiapaqueteria.com\/codigos-postales\/jalisco\/pachaguillo\/"},{"colonia":"Paraíso","col-slug":"paraiso","asentamiento":"Colonia","cp":"45406","estado":"Jalisco","estado-slug":"jalisco","url":"https:\/\/cp.guiapaqueteria.com\/codigos-postales\/jalisco\/paraiso\/"},{"colonia":"Paseo de la Cañada","col-slug":"paseo-de-la-canada","asentamiento":"Fraccionamiento","cp":"45429","estado":"Jalisco","estado-slug":"jalisco","url":"https:\/\/cp.guiapaqueteria.com\/codigos-postales\/jalisco\/paseo-de-la-canada\/"},{"colonia":"Paseo de Tonala","col-slug":"paseo-de-tonala","asentamiento":"Fraccionamiento","cp":"45406","estado":"Jalisco","estado-slug":"jalisco","url":"https:\/\/cp.guiapaqueteria.com\/codigos-postales\/jalisco\/paseo-de-tonala\/"},{"colonia":"Paseos de Santiago","col-slug":"paseos-de-santiago","asentamiento":"Fraccionamiento","cp":"45410","estado":"Jalisco","estado-slug":"jalisco","url":"https:\/\/cp.guiapaqueteria.com\/codigos-postales\/jalisco\/paseos-de-santiago\/"},{"colonia":"Paseos Del Valle","col-slug":"paseos-del-valle","asentamiento":"Colonia","cp":"45403","estado":"Jalisco","estado-slug":"jalisco","url":"https:\/\/cp.guiapaqueteria.com\/codigos-postales\/jalisco\/paseos-del-valle\/"},{"colonia":"Pedregal","col-slug":"pedregal","asentamiento":"Colonia","cp":"45402","estado":"Jalisco","estado-slug":"jalisco","url":"https:\/\/cp.guiapaqueteria.com\/codigos-postales\/jalisco\/pedregal\/"},{"colonia":"Pedregal de Santa Martha","col-slug":"pedregal-de-santa-martha","asentamiento":"Fraccionamiento","cp":"45422","estado":"Jalisco","estado-slug":"jalisco","url":"https:\/\/cp.guiapaqueteria.com\/codigos-postales\/jalisco\/pedregal-de-santa-martha\/"},{"colonia":"Pinar de las Palomas","col-slug":"pinar-de-las-palomas","asentamiento":"Colonia","cp":"45406","estado":"Jalisco","estado-slug":"jalisco","url":"https:\/\/cp.guiapaqueteria.com\/codigos-postales\/jalisco\/pinar-de-las-palomas\/"},{"colonia":"Pirul","col-slug":"pirul","asentamiento":"Colonia","cp":"45400","estado":"Jalisco","estado-slug":"jalisco","url":"https:\/\/cp.guiapaqueteria.com\/codigos-postales\/jalisco\/pirul\/"},{"colonia":"Plan de Guajes","col-slug":"plan-de-guajes","asentamiento":"Colonia","cp":"45415","estado":"Jalisco","estado-slug":"jalisco","url":"https:\/\/cp.guiapaqueteria.com\/codigos-postales\/jalisco\/plan-de-guajes\/"},{"colonia":"Plaza Camichines","col-slug":"plaza-camichines","asentamiento":"Residencial","cp":"45403","estado":"Jalisco","estado-slug":"jalisco","url":"https:\/\/cp.guiapaqueteria.com\/codigos-postales\/jalisco\/plaza-camichines\/"},{"colonia":"Potrerillo","col-slug":"potrerillo","asentamiento":"Colonia","cp":"45420","estado":"Jalisco","estado-slug":"jalisco","url":"https:\/\/cp.guiapaqueteria.com\/codigos-postales\/jalisco\/potrerillo\/"},{"colonia":"Potrerito Beccerros","col-slug":"potrerito-beccerros","asentamiento":"Colonia","cp":"45400","estado":"Jalisco","estado-slug":"jalisco","url":"https:\/\/cp.guiapaqueteria.com\/codigos-postales\/jalisco\/potrerito-beccerros\/"},{"colonia":"Potrero de San José","col-slug":"potrero-de-san-jose","asentamiento":"Fraccionamiento","cp":"45413","estado":"Jalisco","estado-slug":"jalisco","url":"https:\/\/cp.guiapaqueteria.com\/codigos-postales\/jalisco\/potrero-de-san-jose\/"},{"colonia":"Potrero San Francisco","col-slug":"potrero-san-francisco","asentamiento":"Fraccionamiento","cp":"45406","estado":"Jalisco","estado-slug":"jalisco","url":"https:\/\/cp.guiapaqueteria.com\/codigos-postales\/jalisco\/potrero-san-francisco\/"},{"colonia":"Praderas de Tonallan","col-slug":"praderas-de-tonallan","asentamiento":"Fraccionamiento","cp":"45429","estado":"Jalisco","estado-slug":"jalisco","url":"https:\/\/cp.guiapaqueteria.com\/codigos-postales\/jalisco\/praderas-de-tonallan\/"},{"colonia":"Praderas Del Sol","col-slug":"praderas-del-sol","asentamiento":"Fraccionamiento","cp":"45400","estado":"Jalisco","estado-slug":"jalisco","url":"https:\/\/cp.guiapaqueteria.com\/codigos-postales\/jalisco\/praderas-del-sol\/"},{"colonia":"Prados de Coyula Sección I","col-slug":"prados-de-coyula-seccion-i","asentamiento":"Colonia","cp":"45410","estado":"Jalisco","estado-slug":"jalisco","url":"https:\/\/cp.guiapaqueteria.com\/codigos-postales\/jalisco\/prados-de-coyula-seccion-i\/"},{"colonia":"Prados de Coyula Sección II","col-slug":"prados-de-coyula-seccion-ii","asentamiento":"Colonia","cp":"45410","estado":"Jalisco","estado-slug":"jalisco","url":"https:\/\/cp.guiapaqueteria.com\/codigos-postales\/jalisco\/prados-de-coyula-seccion-ii\/"},{"colonia":"Prados de la Cruz","col-slug":"prados-de-la-cruz","asentamiento":"Fraccionamiento","cp":"45410","estado":"Jalisco","estado-slug":"jalisco","url":"https:\/\/cp.guiapaqueteria.com\/codigos-postales\/jalisco\/prados-de-la-cruz\/"},{"colonia":"Prados Tonalá","col-slug":"prados-tonala","asentamiento":"Colonia","cp":"45400","estado":"Jalisco","estado-slug":"jalisco","url":"https:\/\/cp.guiapaqueteria.com\/codigos-postales\/jalisco\/prados-tonala\/"},{"colonia":"Privadas de la Reyna","col-slug":"privadas-de-la-reyna","asentamiento":"Fraccionamiento","cp":"45410","estado":"Jalisco","estado-slug":"jalisco","url":"https:\/\/cp.guiapaqueteria.com\/codigos-postales\/jalisco\/privadas-de-la-reyna\/"},{"colonia":"Pueblito Del Sol","col-slug":"pueblito-del-sol","asentamiento":"Colonia","cp":"45400","estado":"Jalisco","estado-slug":"jalisco","url":"https:\/\/cp.guiapaqueteria.com\/codigos-postales\/jalisco\/pueblito-del-sol\/"},{"colonia":"Puente Grande","col-slug":"puente-grande","asentamiento":"Pueblo","cp":"45427","estado":"Jalisco","estado-slug":"jalisco","url":"https:\/\/cp.guiapaqueteria.com\/codigos-postales\/jalisco\/puente-grande\/"},{"colonia":"Puente Viejo","col-slug":"puente-viejo","asentamiento":"Fraccionamiento","cp":"45424","estado":"Jalisco","estado-slug":"jalisco","url":"https:\/\/cp.guiapaqueteria.com\/codigos-postales\/jalisco\/puente-viejo\/"},{"colonia":"Puerta del Rosario","col-slug":"puerta-del-rosario","asentamiento":"Colonia","cp":"45404","estado":"Jalisco","estado-slug":"jalisco","url":"https:\/\/cp.guiapaqueteria.com\/codigos-postales\/jalisco\/puerta-del-rosario\/"},{"colonia":"Puerta Sol","col-slug":"puerta-sol","asentamiento":"Fraccionamiento","cp":"45410","estado":"Jalisco","estado-slug":"jalisco","url":"https:\/\/cp.guiapaqueteria.com\/codigos-postales\/jalisco\/puerta-sol\/"},{"colonia":"Puerta Vieja","col-slug":"puerta-vieja","asentamiento":"Fraccionamiento","cp":"45410","estado":"Jalisco","estado-slug":"jalisco","url":"https:\/\/cp.guiapaqueteria.com\/codigos-postales\/jalisco\/puerta-vieja\/"},{"colonia":"Puertas del Sol (Autopista)","col-slug":"puertas-del-sol-autopista","asentamiento":"Fraccionamiento","cp":"45429","estado":"Jalisco","estado-slug":"jalisco","url":"https:\/\/cp.guiapaqueteria.com\/codigos-postales\/jalisco\/puertas-del-sol-autopista\/"},{"colonia":"Puesta Del Sol","col-slug":"puesta-del-sol","asentamiento":"Colonia","cp":"45404","estado":"Jalisco","estado-slug":"jalisco","url":"https:\/\/cp.guiapaqueteria.com\/codigos-postales\/jalisco\/puesta-del-sol\/"},{"colonia":"Quintana Catalina","col-slug":"quintana-catalina","asentamiento":"Colonia","cp":"45402","estado":"Jalisco","estado-slug":"jalisco","url":"https:\/\/cp.guiapaqueteria.com\/codigos-postales\/jalisco\/quintana-catalina\/"},{"colonia":"Quintas del Paraíso","col-slug":"quintas-del-paraiso","asentamiento":"Fraccionamiento","cp":"45406","estado":"Jalisco","estado-slug":"jalisco","url":"https:\/\/cp.guiapaqueteria.com\/codigos-postales\/jalisco\/quintas-del-paraiso\/"},{"colonia":"Rancho de los Alvarez","col-slug":"rancho-de-los-alvarez","asentamiento":"Colonia","cp":"45410","estado":"Jalisco","estado-slug":"jalisco","url":"https:\/\/cp.guiapaqueteria.com\/codigos-postales\/jalisco\/rancho-de-los-alvarez\/"},{"colonia":"Rancho La Cruz","col-slug":"rancho-la-cruz","asentamiento":"Colonia","cp":"45410","estado":"Jalisco","estado-slug":"jalisco","url":"https:\/\/cp.guiapaqueteria.com\/codigos-postales\/jalisco\/rancho-la-cruz\/"},{"colonia":"Rancho Sánchez","col-slug":"rancho-sanchez","asentamiento":"Colonia","cp":"45422","estado":"Jalisco","estado-slug":"jalisco","url":"https:\/\/cp.guiapaqueteria.com\/codigos-postales\/jalisco\/rancho-sanchez\/"},{"colonia":"Real Fresno","col-slug":"real-fresno","asentamiento":"Fraccionamiento","cp":"45427","estado":"Jalisco","estado-slug":"jalisco","url":"https:\/\/cp.guiapaqueteria.com\/codigos-postales\/jalisco\/real-fresno\/"},{"colonia":"Real Patria","col-slug":"real-patria","asentamiento":"Fraccionamiento","cp":"45403","estado":"Jalisco","estado-slug":"jalisco","url":"https:\/\/cp.guiapaqueteria.com\/codigos-postales\/jalisco\/real-patria\/"},{"colonia":"Residencial Misión de Guadalupe","col-slug":"residencial-mision-de-guadalupe","asentamiento":"Fraccionamiento","cp":"45420","estado":"Jalisco","estado-slug":"jalisco","url":"https:\/\/cp.guiapaqueteria.com\/codigos-postales\/jalisco\/residencial-mision-de-guadalupe\/"},{"colonia":"Residencias el Prado (Jardines del Prado)","col-slug":"residencias-el-prado-jardines-del-prado","asentamiento":"Fraccionamiento","cp":"45413","estado":"Jalisco","estado-slug":"jalisco","url":"https:\/\/cp.guiapaqueteria.com\/codigos-postales\/jalisco\/residencias-el-prado-jardines-del-prado\/"},{"colonia":"Rey Xolotl","col-slug":"rey-xolotl","asentamiento":"Condominio","cp":"45402","estado":"Jalisco","estado-slug":"jalisco","url":"https:\/\/cp.guiapaqueteria.com\/codigos-postales\/jalisco\/rey-xolotl\/"},{"colonia":"Rey Xolotl","col-slug":"rey-xolotl","asentamiento":"Colonia","cp":"45402","estado":"Jalisco","estado-slug":"jalisco","url":"https:\/\/cp.guiapaqueteria.com\/codigos-postales\/jalisco\/rey-xolotl\/"},{"colonia":"Reyna Alta","col-slug":"reyna-alta","asentamiento":"Fraccionamiento","cp":"45410","estado":"Jalisco","estado-slug":"jalisco","url":"https:\/\/cp.guiapaqueteria.com\/codigos-postales\/jalisco\/reyna-alta\/"},{"colonia":"Ricardo Flores Magón","col-slug":"ricardo-flores-magon","asentamiento":"Colonia","cp":"45400","estado":"Jalisco","estado-slug":"jalisco","url":"https:\/\/cp.guiapaqueteria.com\/codigos-postales\/jalisco\/ricardo-flores-magon\/"},{"colonia":"Rincón del Paraíso","col-slug":"rincon-del-paraiso","asentamiento":"Fraccionamiento","cp":"45406","estado":"Jalisco","estado-slug":"jalisco","url":"https:\/\/cp.guiapaqueteria.com\/codigos-postales\/jalisco\/rincon-del-paraiso\/"},{"colonia":"Rinconada de Coyula","col-slug":"rinconada-de-coyula","asentamiento":"Colonia","cp":"45410","estado":"Jalisco","estado-slug":"jalisco","url":"https:\/\/cp.guiapaqueteria.com\/codigos-postales\/jalisco\/rinconada-de-coyula\/"},{"colonia":"Rinconada de La Cruz","col-slug":"rinconada-de-la-cruz","asentamiento":"Fraccionamiento","cp":"45410","estado":"Jalisco","estado-slug":"jalisco","url":"https:\/\/cp.guiapaqueteria.com\/codigos-postales\/jalisco\/rinconada-de-la-cruz\/"},{"colonia":"Rinconada de la Presa","col-slug":"rinconada-de-la-presa","asentamiento":"Fraccionamiento","cp":"45403","estado":"Jalisco","estado-slug":"jalisco","url":"https:\/\/cp.guiapaqueteria.com\/codigos-postales\/jalisco\/rinconada-de-la-presa\/"},{"colonia":"Rinconada de la Providencia","col-slug":"rinconada-de-la-providencia","asentamiento":"Fraccionamiento","cp":"45420","estado":"Jalisco","estado-slug":"jalisco","url":"https:\/\/cp.guiapaqueteria.com\/codigos-postales\/jalisco\/rinconada-de-la-providencia\/"},{"colonia":"Rinconada de los Cerezos","col-slug":"rinconada-de-los-cerezos","asentamiento":"Fraccionamiento","cp":"45400","estado":"Jalisco","estado-slug":"jalisco","url":"https:\/\/cp.guiapaqueteria.com\/codigos-postales\/jalisco\/rinconada-de-los-cerezos\/"},{"colonia":"Rinconada de San Lorenzo","col-slug":"rinconada-de-san-lorenzo","asentamiento":"Fraccionamiento","cp":"45410","estado":"Jalisco","estado-slug":"jalisco","url":"https:\/\/cp.guiapaqueteria.com\/codigos-postales\/jalisco\/rinconada-de-san-lorenzo\/"},{"colonia":"Rinconada del Árbol","col-slug":"rinconada-del-arbol","asentamiento":"Fraccionamiento","cp":"45403","estado":"Jalisco","estado-slug":"jalisco","url":"https:\/\/cp.guiapaqueteria.com\/codigos-postales\/jalisco\/rinconada-del-arbol\/"},{"colonia":"Rinconada del Huerto","col-slug":"rinconada-del-huerto","asentamiento":"Fraccionamiento","cp":"45404","estado":"Jalisco","estado-slug":"jalisco","url":"https:\/\/cp.guiapaqueteria.com\/codigos-postales\/jalisco\/rinconada-del-huerto\/"},{"colonia":"Rinconada Del Mezquital","col-slug":"rinconada-del-mezquital","asentamiento":"Fraccionamiento","cp":"45405","estado":"Jalisco","estado-slug":"jalisco","url":"https:\/\/cp.guiapaqueteria.com\/codigos-postales\/jalisco\/rinconada-del-mezquital\/"},{"colonia":"Rinconada del Parque","col-slug":"rinconada-del-parque","asentamiento":"Condominio","cp":"45406","estado":"Jalisco","estado-slug":"jalisco","url":"https:\/\/cp.guiapaqueteria.com\/codigos-postales\/jalisco\/rinconada-del-parque\/"},{"colonia":"Rinconada del Rosario","col-slug":"rinconada-del-rosario","asentamiento":"Colonia","cp":"45404","estado":"Jalisco","estado-slug":"jalisco","url":"https:\/\/cp.guiapaqueteria.com\/codigos-postales\/jalisco\/rinconada-del-rosario\/"},{"colonia":"Rinconada Paraíso","col-slug":"rinconada-paraiso","asentamiento":"Fraccionamiento","cp":"45406","estado":"Jalisco","estado-slug":"jalisco","url":"https:\/\/cp.guiapaqueteria.com\/codigos-postales\/jalisco\/rinconada-paraiso\/"},{"colonia":"Rinconada San Francisco","col-slug":"rinconada-san-francisco","asentamiento":"Colonia","cp":"45403","estado":"Jalisco","estado-slug":"jalisco","url":"https:\/\/cp.guiapaqueteria.com\/codigos-postales\/jalisco\/rinconada-san-francisco\/"},{"colonia":"Rinconada Tonalá","col-slug":"rinconada-tonala","asentamiento":"Fraccionamiento","cp":"45400","estado":"Jalisco","estado-slug":"jalisco","url":"https:\/\/cp.guiapaqueteria.com\/codigos-postales\/jalisco\/rinconada-tonala\/"},{"colonia":"Rinconadas Del Sol","col-slug":"rinconadas-del-sol","asentamiento":"Fraccionamiento","cp":"45400","estado":"Jalisco","estado-slug":"jalisco","url":"https:\/\/cp.guiapaqueteria.com\/codigos-postales\/jalisco\/rinconadas-del-sol\/"},{"colonia":"San Elias","col-slug":"san-elias","asentamiento":"Fraccionamiento","cp":"45400","estado":"Jalisco","estado-slug":"jalisco","url":"https:\/\/cp.guiapaqueteria.com\/codigos-postales\/jalisco\/san-elias\/"},{"colonia":"San Francisco de la Soledad","col-slug":"san-francisco-de-la-soledad","asentamiento":"Colonia","cp":"45424","estado":"Jalisco","estado-slug":"jalisco","url":"https:\/\/cp.guiapaqueteria.com\/codigos-postales\/jalisco\/san-francisco-de-la-soledad\/"},{"colonia":"San Gaspar de las Flores","col-slug":"san-gaspar-de-las-flores","asentamiento":"Colonia","cp":"45408","estado":"Jalisco","estado-slug":"jalisco","url":"https:\/\/cp.guiapaqueteria.com\/codigos-postales\/jalisco\/san-gaspar-de-las-flores\/"},{"colonia":"San Jorge","col-slug":"san-jorge","asentamiento":"Fraccionamiento","cp":"45427","estado":"Jalisco","estado-slug":"jalisco","url":"https:\/\/cp.guiapaqueteria.com\/codigos-postales\/jalisco\/san-jorge\/"},{"colonia":"San Mateo","col-slug":"san-mateo","asentamiento":"Fraccionamiento","cp":"45400","estado":"Jalisco","estado-slug":"jalisco","url":"https:\/\/cp.guiapaqueteria.com\/codigos-postales\/jalisco\/san-mateo\/"},{"colonia":"San Miguel de La Punta","col-slug":"san-miguel-de-la-punta","asentamiento":"Ranchería","cp":"45425","estado":"Jalisco","estado-slug":"jalisco","url":"https:\/\/cp.guiapaqueteria.com\/codigos-postales\/jalisco\/san-miguel-de-la-punta\/"},{"colonia":"Santa Cruz de las Huertas","col-slug":"santa-cruz-de-las-huertas","asentamiento":"Colonia","cp":"45402","estado":"Jalisco","estado-slug":"jalisco","url":"https:\/\/cp.guiapaqueteria.com\/codigos-postales\/jalisco\/santa-cruz-de-las-huertas\/"},{"colonia":"Santa Isabel","col-slug":"santa-isabel","asentamiento":"Colonia","cp":"45420","estado":"Jalisco","estado-slug":"jalisco","url":"https:\/\/cp.guiapaqueteria.com\/codigos-postales\/jalisco\/santa-isabel\/"},{"colonia":"Santa Paula","col-slug":"santa-paula","asentamiento":"Colonia","cp":"45420","estado":"Jalisco","estado-slug":"jalisco","url":"https:\/\/cp.guiapaqueteria.com\/codigos-postales\/jalisco\/santa-paula\/"},{"colonia":"Santa Rosa","col-slug":"santa-rosa","asentamiento":"Colonia","cp":"45420","estado":"Jalisco","estado-slug":"jalisco","url":"https:\/\/cp.guiapaqueteria.com\/codigos-postales\/jalisco\/santa-rosa\/"},{"colonia":"Senderos de Santiago","col-slug":"senderos-de-santiago","asentamiento":"Fraccionamiento","cp":"45410","estado":"Jalisco","estado-slug":"jalisco","url":"https:\/\/cp.guiapaqueteria.com\/codigos-postales\/jalisco\/senderos-de-santiago\/"},{"colonia":"Sillita Zapote","col-slug":"sillita-zapote","asentamiento":"Colonia","cp":"45400","estado":"Jalisco","estado-slug":"jalisco","url":"https:\/\/cp.guiapaqueteria.com\/codigos-postales\/jalisco\/sillita-zapote\/"},{"colonia":"Surcos Largos","col-slug":"surcos-largos","asentamiento":"Colonia","cp":"45413","estado":"Jalisco","estado-slug":"jalisco","url":"https:\/\/cp.guiapaqueteria.com\/codigos-postales\/jalisco\/surcos-largos\/"},{"colonia":"Tenamaxtle","col-slug":"tenamaxtle","asentamiento":"Colonia","cp":"45400","estado":"Jalisco","estado-slug":"jalisco","url":"https:\/\/cp.guiapaqueteria.com\/codigos-postales\/jalisco\/tenamaxtle\/"},{"colonia":"Tololotlán","col-slug":"tololotlan","asentamiento":"Colonia","cp":"45427","estado":"Jalisco","estado-slug":"jalisco","url":"https:\/\/cp.guiapaqueteria.com\/codigos-postales\/jalisco\/tololotlan\/"},{"colonia":"Tonalá Centro","col-slug":"tonala-centro","asentamiento":"Colonia","cp":"45400","estado":"Jalisco","estado-slug":"jalisco","url":"https:\/\/cp.guiapaqueteria.com\/codigos-postales\/jalisco\/tonala-centro\/"},{"colonia":"Tonaltecas","col-slug":"tonaltecas","asentamiento":"Colonia","cp":"45400","estado":"Jalisco","estado-slug":"jalisco","url":"https:\/\/cp.guiapaqueteria.com\/codigos-postales\/jalisco\/tonaltecas\/"},{"colonia":"Tonaltecas II","col-slug":"tonaltecas-ii","asentamiento":"Colonia","cp":"45400","estado":"Jalisco","estado-slug":"jalisco","url":"https:\/\/cp.guiapaqueteria.com\/codigos-postales\/jalisco\/tonaltecas-ii\/"},{"colonia":"Tulipanes","col-slug":"tulipanes","asentamiento":"Colonia","cp":"45413","estado":"Jalisco","estado-slug":"jalisco","url":"https:\/\/cp.guiapaqueteria.com\/codigos-postales\/jalisco\/tulipanes\/"},{"colonia":"Urbi Quinta Montecarlo","col-slug":"urbi-quinta-montecarlo","asentamiento":"Fraccionamiento","cp":"45410","estado":"Jalisco","estado-slug":"jalisco","url":"https:\/\/cp.guiapaqueteria.com\/codigos-postales\/jalisco\/urbi-quinta-montecarlo\/"},{"colonia":"Urbi Villa del Río","col-slug":"urbi-villa-del-rio","asentamiento":"Fraccionamiento","cp":"45410","estado":"Jalisco","estado-slug":"jalisco","url":"https:\/\/cp.guiapaqueteria.com\/codigos-postales\/jalisco\/urbi-villa-del-rio\/"},{"colonia":"Valle de La Reyna","col-slug":"valle-de-la-reyna","asentamiento":"Fraccionamiento","cp":"45404","estado":"Jalisco","estado-slug":"jalisco","url":"https:\/\/cp.guiapaqueteria.com\/codigos-postales\/jalisco\/valle-de-la-reyna\/"},{"colonia":"Valle de Tonantzin","col-slug":"valle-de-tonantzin","asentamiento":"Fraccionamiento","cp":"45410","estado":"Jalisco","estado-slug":"jalisco","url":"https:\/\/cp.guiapaqueteria.com\/codigos-postales\/jalisco\/valle-de-tonantzin\/"},{"colonia":"Valle Del Sol","col-slug":"valle-del-sol","asentamiento":"Colonia","cp":"45400","estado":"Jalisco","estado-slug":"jalisco","url":"https:\/\/cp.guiapaqueteria.com\/codigos-postales\/jalisco\/valle-del-sol\/"},{"colonia":"Valle Leones","col-slug":"valle-leones","asentamiento":"Fraccionamiento","cp":"45404","estado":"Jalisco","estado-slug":"jalisco","url":"https:\/\/cp.guiapaqueteria.com\/codigos-postales\/jalisco\/valle-leones\/"},{"colonia":"Valle Verde","col-slug":"valle-verde","asentamiento":"Fraccionamiento","cp":"45410","estado":"Jalisco","estado-slug":"jalisco","url":"https:\/\/cp.guiapaqueteria.com\/codigos-postales\/jalisco\/valle-verde\/"},{"colonia":"Vasconcelos","col-slug":"vasconcelos","asentamiento":"Colonia","cp":"45425","estado":"Jalisco","estado-slug":"jalisco","url":"https:\/\/cp.guiapaqueteria.com\/codigos-postales\/jalisco\/vasconcelos\/"},{"colonia":"Vergel","col-slug":"vergel","asentamiento":"Colonia","cp":"45410","estado":"Jalisco","estado-slug":"jalisco","url":"https:\/\/cp.guiapaqueteria.com\/codigos-postales\/jalisco\/vergel\/"},{"colonia":"Verona","col-slug":"verona","asentamiento":"Condominio","cp":"45410","estado":"Jalisco","estado-slug":"jalisco","url":"https:\/\/cp.guiapaqueteria.com\/codigos-postales\/jalisco\/verona\/"},{"colonia":"Vía Nova","col-slug":"via-nova","asentamiento":"Fraccionamiento","cp":"45410","estado":"Jalisco","estado-slug":"jalisco","url":"https:\/\/cp.guiapaqueteria.com\/codigos-postales\/jalisco\/via-nova\/"},{"colonia":"Villas Artesanos","col-slug":"villas-artesanos","asentamiento":"Fraccionamiento","cp":"45402","estado":"Jalisco","estado-slug":"jalisco","url":"https:\/\/cp.guiapaqueteria.com\/codigos-postales\/jalisco\/villas-artesanos\/"},{"colonia":"Villas Cruz","col-slug":"villas-cruz","asentamiento":"Colonia","cp":"45410","estado":"Jalisco","estado-slug":"jalisco","url":"https:\/\/cp.guiapaqueteria.com\/codigos-postales\/jalisco\/villas-cruz\/"},{"colonia":"Villas de Oriente","col-slug":"villas-de-oriente","asentamiento":"Colonia","cp":"45403","estado":"Jalisco","estado-slug":"jalisco","url":"https:\/\/cp.guiapaqueteria.com\/codigos-postales\/jalisco\/villas-de-oriente\/"},{"colonia":"Villas de Oriente II","col-slug":"villas-de-oriente-ii","asentamiento":"Colonia","cp":"45403","estado":"Jalisco","estado-slug":"jalisco","url":"https:\/\/cp.guiapaqueteria.com\/codigos-postales\/jalisco\/villas-de-oriente-ii\/"},{"colonia":"Villas de Santiago","col-slug":"villas-de-santiago","asentamiento":"Fraccionamiento","cp":"45410","estado":"Jalisco","estado-slug":"jalisco","url":"https:\/\/cp.guiapaqueteria.com\/codigos-postales\/jalisco\/villas-de-santiago\/"},{"colonia":"Villas del Pinar","col-slug":"villas-del-pinar","asentamiento":"Fraccionamiento","cp":"45406","estado":"Jalisco","estado-slug":"jalisco","url":"https:\/\/cp.guiapaqueteria.com\/codigos-postales\/jalisco\/villas-del-pinar\/"},{"colonia":"Villas Zalatitán","col-slug":"villas-zalatitan","asentamiento":"Colonia","cp":"45406","estado":"Jalisco","estado-slug":"jalisco","url":"https:\/\/cp.guiapaqueteria.com\/codigos-postales\/jalisco\/villas-zalatitan\/"},{"colonia":"Vistas del Pedregal","col-slug":"vistas-del-pedregal","asentamiento":"Fraccionamiento","cp":"45422","estado":"Jalisco","estado-slug":"jalisco","url":"https:\/\/cp.guiapaqueteria.com\/codigos-postales\/jalisco\/vistas-del-pedregal\/"},{"colonia":"Vistas del Rey","col-slug":"vistas-del-rey","asentamiento":"Fraccionamiento","cp":"45402","estado":"Jalisco","estado-slug":"jalisco","url":"https:\/\/cp.guiapaqueteria.com\/codigos-postales\/jalisco\/vistas-del-rey\/"},{"colonia":"Vistas del Tonallan","col-slug":"vistas-del-tonallan","asentamiento":"Fraccionamiento","cp":"45429","estado":"Jalisco","estado-slug":"jalisco","url":"https:\/\/cp.guiapaqueteria.com\/codigos-postales\/jalisco\/vistas-del-tonallan\/"},{"colonia":"Vistas del Valle","col-slug":"vistas-del-valle","asentamiento":"Fraccionamiento","cp":"45400","estado":"Jalisco","estado-slug":"jalisco","url":"https:\/\/cp.guiapaqueteria.com\/codigos-postales\/jalisco\/vistas-del-valle\/"},{"colonia":"Vistas Tonallán","col-slug":"vistas-tonallan","asentamiento":"Fraccionamiento","cp":"45400","estado":"Jalisco","estado-slug":"jalisco","url":"https:\/\/cp.guiapaqueteria.com\/codigos-postales\/jalisco\/vistas-tonallan\/"},{"colonia":"Xicoxochitl","col-slug":"xicoxochitl","asentamiento":"Colonia","cp":"45400","estado":"Jalisco","estado-slug":"jalisco","url":"https:\/\/cp.guiapaqueteria.com\/codigos-postales\/jalisco\/xicoxochitl\/"},{"colonia":"Zalatitan","col-slug":"zalatitan","asentamiento":"Colonia","cp":"45405","estado":"Jalisco","estado-slug":"jalisco","url":"https:\/\/cp.guiapaqueteria.com\/codigos-postales\/jalisco\/zalatitan\/"}]