[{"colonia":"Amacuautitlán","col-slug":"amacuautitlan","asentamiento":"Ranchería","cp":"48764","estado":"Jalisco","estado-slug":"jalisco","url":"https:\/\/cp.guiapaqueteria.com\/codigos-postales\/jalisco\/amacuautitlan\/"},{"colonia":"Atarjeas de Covarrubias (San Isidro)","col-slug":"atarjeas-de-covarrubias-san-isidro","asentamiento":"Ranchería","cp":"48769","estado":"Jalisco","estado-slug":"jalisco","url":"https:\/\/cp.guiapaqueteria.com\/codigos-postales\/jalisco\/atarjeas-de-covarrubias-san-isidro\/"},{"colonia":"Coatlancillo","col-slug":"coatlancillo","asentamiento":"Congregación","cp":"48765","estado":"Jalisco","estado-slug":"jalisco","url":"https:\/\/cp.guiapaqueteria.com\/codigos-postales\/jalisco\/coatlancillo\/"},{"colonia":"El Cerrito","col-slug":"el-cerrito","asentamiento":"Congregación","cp":"48767","estado":"Jalisco","estado-slug":"jalisco","url":"https:\/\/cp.guiapaqueteria.com\/codigos-postales\/jalisco\/el-cerrito\/"},{"colonia":"El Paso de San Francisco","col-slug":"el-paso-de-san-francisco","asentamiento":"Ranchería","cp":"48766","estado":"Jalisco","estado-slug":"jalisco","url":"https:\/\/cp.guiapaqueteria.com\/codigos-postales\/jalisco\/el-paso-de-san-francisco\/"},{"colonia":"Guadalupana","col-slug":"guadalupana","asentamiento":"Colonia","cp":"48760","estado":"Jalisco","estado-slug":"jalisco","url":"https:\/\/cp.guiapaqueteria.com\/codigos-postales\/jalisco\/guadalupana\/"},{"colonia":"La Aviación","col-slug":"la-aviacion","asentamiento":"Colonia","cp":"48760","estado":"Jalisco","estado-slug":"jalisco","url":"https:\/\/cp.guiapaqueteria.com\/codigos-postales\/jalisco\/la-aviacion\/"},{"colonia":"La Cofradía","col-slug":"la-cofradia","asentamiento":"Colonia","cp":"48760","estado":"Jalisco","estado-slug":"jalisco","url":"https:\/\/cp.guiapaqueteria.com\/codigos-postales\/jalisco\/la-cofradia\/"},{"colonia":"Las Higueras","col-slug":"las-higueras","asentamiento":"Ranchería","cp":"48766","estado":"Jalisco","estado-slug":"jalisco","url":"https:\/\/cp.guiapaqueteria.com\/codigos-postales\/jalisco\/las-higueras\/"},{"colonia":"Las Liebres","col-slug":"las-liebres","asentamiento":"Ranchería","cp":"48763","estado":"Jalisco","estado-slug":"jalisco","url":"https:\/\/cp.guiapaqueteria.com\/codigos-postales\/jalisco\/las-liebres\/"},{"colonia":"Los Asmoles","col-slug":"los-asmoles","asentamiento":"Ranchería","cp":"48768","estado":"Jalisco","estado-slug":"jalisco","url":"https:\/\/cp.guiapaqueteria.com\/codigos-postales\/jalisco\/los-asmoles\/"},{"colonia":"Los Gonzalez","col-slug":"los-gonzalez","asentamiento":"Congregación","cp":"48763","estado":"Jalisco","estado-slug":"jalisco","url":"https:\/\/cp.guiapaqueteria.com\/codigos-postales\/jalisco\/los-gonzalez\/"},{"colonia":"San Luis Tenango","col-slug":"san-luis-tenango","asentamiento":"Ranchería","cp":"48760","estado":"Jalisco","estado-slug":"jalisco","url":"https:\/\/cp.guiapaqueteria.com\/codigos-postales\/jalisco\/san-luis-tenango\/"},{"colonia":"Tonaya","col-slug":"tonaya","asentamiento":"Pueblo","cp":"48760","estado":"Jalisco","estado-slug":"jalisco","url":"https:\/\/cp.guiapaqueteria.com\/codigos-postales\/jalisco\/tonaya\/"}]