[{"colonia":"2 de Abril","col-slug":"2-de-abril","asentamiento":"Colonia","cp":"43863","estado":"Hidalgo","estado-slug":"hidalgo","url":"https:\/\/cp.guiapaqueteria.com\/codigos-postales\/hidalgo\/2-de-abril\/"},{"colonia":"Bloquera","col-slug":"bloquera","asentamiento":"Ranchería","cp":"43874","estado":"Hidalgo","estado-slug":"hidalgo","url":"https:\/\/cp.guiapaqueteria.com\/codigos-postales\/hidalgo\/bloquera\/"},{"colonia":"El Cerrito","col-slug":"el-cerrito","asentamiento":"Colonia","cp":"43864","estado":"Hidalgo","estado-slug":"hidalgo","url":"https:\/\/cp.guiapaqueteria.com\/codigos-postales\/hidalgo\/el-cerrito\/"},{"colonia":"El Pavo Real","col-slug":"el-pavo-real","asentamiento":"Ranchería","cp":"43867","estado":"Hidalgo","estado-slug":"hidalgo","url":"https:\/\/cp.guiapaqueteria.com\/codigos-postales\/hidalgo\/el-pavo-real\/"},{"colonia":"El Tejocote","col-slug":"el-tejocote","asentamiento":"Ranchería","cp":"43866","estado":"Hidalgo","estado-slug":"hidalgo","url":"https:\/\/cp.guiapaqueteria.com\/codigos-postales\/hidalgo\/el-tejocote\/"},{"colonia":"Epitacio Mendoza","col-slug":"epitacio-mendoza","asentamiento":"Colonia","cp":"43863","estado":"Hidalgo","estado-slug":"hidalgo","url":"https:\/\/cp.guiapaqueteria.com\/codigos-postales\/hidalgo\/epitacio-mendoza\/"},{"colonia":"Esteban Meneses Corona","col-slug":"esteban-meneses-corona","asentamiento":"Ranchería","cp":"43866","estado":"Hidalgo","estado-slug":"hidalgo","url":"https:\/\/cp.guiapaqueteria.com\/codigos-postales\/hidalgo\/esteban-meneses-corona\/"},{"colonia":"General Felipe Ángeles","col-slug":"general-felipe-angeles","asentamiento":"Colonia","cp":"43875","estado":"Hidalgo","estado-slug":"hidalgo","url":"https:\/\/cp.guiapaqueteria.com\/codigos-postales\/hidalgo\/general-felipe-angeles\/"},{"colonia":"Granja los Pinos","col-slug":"granja-los-pinos","asentamiento":"Ranchería","cp":"43862","estado":"Hidalgo","estado-slug":"hidalgo","url":"https:\/\/cp.guiapaqueteria.com\/codigos-postales\/hidalgo\/granja-los-pinos\/"},{"colonia":"Independencia","col-slug":"independencia","asentamiento":"Colonia","cp":"43863","estado":"Hidalgo","estado-slug":"hidalgo","url":"https:\/\/cp.guiapaqueteria.com\/codigos-postales\/hidalgo\/independencia\/"},{"colonia":"La Casa Enterrada","col-slug":"la-casa-enterrada","asentamiento":"Ranchería","cp":"43865","estado":"Hidalgo","estado-slug":"hidalgo","url":"https:\/\/cp.guiapaqueteria.com\/codigos-postales\/hidalgo\/la-casa-enterrada\/"},{"colonia":"La Colmena","col-slug":"la-colmena","asentamiento":"Colonia","cp":"43864","estado":"Hidalgo","estado-slug":"hidalgo","url":"https:\/\/cp.guiapaqueteria.com\/codigos-postales\/hidalgo\/la-colmena\/"},{"colonia":"La Gloria Escondida (Rancho de la Cruz)","col-slug":"la-gloria-escondida-rancho-de-la-cruz","asentamiento":"Ranchería","cp":"43874","estado":"Hidalgo","estado-slug":"hidalgo","url":"https:\/\/cp.guiapaqueteria.com\/codigos-postales\/hidalgo\/la-gloria-escondida-rancho-de-la-cruz\/"},{"colonia":"La Palma","col-slug":"la-palma","asentamiento":"Colonia","cp":"43864","estado":"Hidalgo","estado-slug":"hidalgo","url":"https:\/\/cp.guiapaqueteria.com\/codigos-postales\/hidalgo\/la-palma\/"},{"colonia":"Las Palomas","col-slug":"las-palomas","asentamiento":"Ranchería","cp":"43866","estado":"Hidalgo","estado-slug":"hidalgo","url":"https:\/\/cp.guiapaqueteria.com\/codigos-postales\/hidalgo\/las-palomas\/"},{"colonia":"Las Pintas","col-slug":"las-pintas","asentamiento":"Colonia","cp":"43873","estado":"Hidalgo","estado-slug":"hidalgo","url":"https:\/\/cp.guiapaqueteria.com\/codigos-postales\/hidalgo\/las-pintas\/"},{"colonia":"Lomas de San Miguel","col-slug":"lomas-de-san-miguel","asentamiento":"Ranchería","cp":"43874","estado":"Hidalgo","estado-slug":"hidalgo","url":"https:\/\/cp.guiapaqueteria.com\/codigos-postales\/hidalgo\/lomas-de-san-miguel\/"},{"colonia":"Lomas del Álamo","col-slug":"lomas-del-alamo","asentamiento":"Fraccionamiento","cp":"43865","estado":"Hidalgo","estado-slug":"hidalgo","url":"https:\/\/cp.guiapaqueteria.com\/codigos-postales\/hidalgo\/lomas-del-alamo\/"},{"colonia":"Los Amores de Don Juan","col-slug":"los-amores-de-don-juan","asentamiento":"Fraccionamiento","cp":"43863","estado":"Hidalgo","estado-slug":"hidalgo","url":"https:\/\/cp.guiapaqueteria.com\/codigos-postales\/hidalgo\/los-amores-de-don-juan\/"},{"colonia":"María Guadalupe Figueroa Gutiérrez","col-slug":"maria-guadalupe-figueroa-gutierrez","asentamiento":"Ranchería","cp":"43876","estado":"Hidalgo","estado-slug":"hidalgo","url":"https:\/\/cp.guiapaqueteria.com\/codigos-postales\/hidalgo\/maria-guadalupe-figueroa-gutierrez\/"},{"colonia":"Matías Rodríguez el Mambrú","col-slug":"matias-rodriguez-el-mambru","asentamiento":"Ranchería","cp":"43865","estado":"Hidalgo","estado-slug":"hidalgo","url":"https:\/\/cp.guiapaqueteria.com\/codigos-postales\/hidalgo\/matias-rodriguez-el-mambru\/"},{"colonia":"Miravalle","col-slug":"miravalle","asentamiento":"Ranchería","cp":"43866","estado":"Hidalgo","estado-slug":"hidalgo","url":"https:\/\/cp.guiapaqueteria.com\/codigos-postales\/hidalgo\/miravalle\/"},{"colonia":"Rafael Mejia","col-slug":"rafael-mejia","asentamiento":"Ranchería","cp":"43865","estado":"Hidalgo","estado-slug":"hidalgo","url":"https:\/\/cp.guiapaqueteria.com\/codigos-postales\/hidalgo\/rafael-mejia\/"},{"colonia":"San Miguel Eyacalco","col-slug":"san-miguel-eyacalco","asentamiento":"Ranchería","cp":"43870","estado":"Hidalgo","estado-slug":"hidalgo","url":"https:\/\/cp.guiapaqueteria.com\/codigos-postales\/hidalgo\/san-miguel-eyacalco\/"},{"colonia":"Santiago Tlajomulco","col-slug":"santiago-tlajomulco","asentamiento":"Pueblo","cp":"43865","estado":"Hidalgo","estado-slug":"hidalgo","url":"https:\/\/cp.guiapaqueteria.com\/codigos-postales\/hidalgo\/santiago-tlajomulco\/"},{"colonia":"Santo Tomás","col-slug":"santo-tomas","asentamiento":"Colonia","cp":"43863","estado":"Hidalgo","estado-slug":"hidalgo","url":"https:\/\/cp.guiapaqueteria.com\/codigos-postales\/hidalgo\/santo-tomas\/"},{"colonia":"Satélite","col-slug":"satelite","asentamiento":"Colonia","cp":"43864","estado":"Hidalgo","estado-slug":"hidalgo","url":"https:\/\/cp.guiapaqueteria.com\/codigos-postales\/hidalgo\/satelite\/"},{"colonia":"Tildio","col-slug":"tildio","asentamiento":"Colonia","cp":"43863","estado":"Hidalgo","estado-slug":"hidalgo","url":"https:\/\/cp.guiapaqueteria.com\/codigos-postales\/hidalgo\/tildio\/"},{"colonia":"Tolcayuca Centro","col-slug":"tolcayuca-centro","asentamiento":"Colonia","cp":"43860","estado":"Hidalgo","estado-slug":"hidalgo","url":"https:\/\/cp.guiapaqueteria.com\/codigos-postales\/hidalgo\/tolcayuca-centro\/"},{"colonia":"Vicente Guerrero (San Javier)","col-slug":"vicente-guerrero-san-javier","asentamiento":"Pueblo","cp":"43862","estado":"Hidalgo","estado-slug":"hidalgo","url":"https:\/\/cp.guiapaqueteria.com\/codigos-postales\/hidalgo\/vicente-guerrero-san-javier\/"}]