[{"colonia":"Agua Fría (La Cañada)","col-slug":"agua-fria-la-canada","asentamiento":"Ranchería","cp":"61063","estado":"Michoacán","estado-slug":"michoacan","url":"https:\/\/cp.guiapaqueteria.com\/codigos-postales\/michoacan\/agua-fria-la-canada\/"},{"colonia":"Barrio Cuatro Caminos","col-slug":"barrio-cuatro-caminos","asentamiento":"Colonia","cp":"61060","estado":"Michoacán","estado-slug":"michoacan","url":"https:\/\/cp.guiapaqueteria.com\/codigos-postales\/michoacan\/barrio-cuatro-caminos\/"},{"colonia":"Campo Azul (La Presa)","col-slug":"campo-azul-la-presa","asentamiento":"Ranchería","cp":"61063","estado":"Michoacán","estado-slug":"michoacan","url":"https:\/\/cp.guiapaqueteria.com\/codigos-postales\/michoacan\/campo-azul-la-presa\/"},{"colonia":"Cerrito de Rubí","col-slug":"cerrito-de-rubi","asentamiento":"Ranchería","cp":"61072","estado":"Michoacán","estado-slug":"michoacan","url":"https:\/\/cp.guiapaqueteria.com\/codigos-postales\/michoacan\/cerrito-de-rubi\/"},{"colonia":"Cerro Alto","col-slug":"cerro-alto","asentamiento":"Ranchería","cp":"61086","estado":"Michoacán","estado-slug":"michoacan","url":"https:\/\/cp.guiapaqueteria.com\/codigos-postales\/michoacan\/cerro-alto\/"},{"colonia":"Cerro Prieto","col-slug":"cerro-prieto","asentamiento":"Ranchería","cp":"61074","estado":"Michoacán","estado-slug":"michoacan","url":"https:\/\/cp.guiapaqueteria.com\/codigos-postales\/michoacan\/cerro-prieto\/"},{"colonia":"Chalmita (Chazmiti)","col-slug":"chalmita-chazmiti","asentamiento":"Ranchería","cp":"61082","estado":"Michoacán","estado-slug":"michoacan","url":"https:\/\/cp.guiapaqueteria.com\/codigos-postales\/michoacan\/chalmita-chazmiti\/"},{"colonia":"Coloradillas","col-slug":"coloradillas","asentamiento":"Ranchería","cp":"61083","estado":"Michoacán","estado-slug":"michoacan","url":"https:\/\/cp.guiapaqueteria.com\/codigos-postales\/michoacan\/coloradillas\/"},{"colonia":"Cortaduras","col-slug":"cortaduras","asentamiento":"Ranchería","cp":"61080","estado":"Michoacán","estado-slug":"michoacan","url":"https:\/\/cp.guiapaqueteria.com\/codigos-postales\/michoacan\/cortaduras\/"},{"colonia":"Dos Estrellas","col-slug":"dos-estrellas","asentamiento":"Poblado comunal","cp":"61062","estado":"Michoacán","estado-slug":"michoacan","url":"https:\/\/cp.guiapaqueteria.com\/codigos-postales\/michoacan\/dos-estrellas\/"},{"colonia":"Ejido San Lorenzo","col-slug":"ejido-san-lorenzo","asentamiento":"Ranchería","cp":"61065","estado":"Michoacán","estado-slug":"michoacan","url":"https:\/\/cp.guiapaqueteria.com\/codigos-postales\/michoacan\/ejido-san-lorenzo\/"},{"colonia":"El Calco","col-slug":"el-calco","asentamiento":"Colonia","cp":"61060","estado":"Michoacán","estado-slug":"michoacan","url":"https:\/\/cp.guiapaqueteria.com\/codigos-postales\/michoacan\/el-calco\/"},{"colonia":"El Capulín (Cuartel Tercero San Joaquín Morelos)","col-slug":"el-capulin-cuartel-tercero-san-joaquin-morelos","asentamiento":"Ranchería","cp":"61073","estado":"Michoacán","estado-slug":"michoacan","url":"https:\/\/cp.guiapaqueteria.com\/codigos-postales\/michoacan\/el-capulin-cuartel-tercero-san-joaquin-morelos\/"},{"colonia":"El Carmen","col-slug":"el-carmen","asentamiento":"Colonia","cp":"61060","estado":"Michoacán","estado-slug":"michoacan","url":"https:\/\/cp.guiapaqueteria.com\/codigos-postales\/michoacan\/el-carmen\/"},{"colonia":"El Colorín","col-slug":"el-colorin","asentamiento":"Ranchería","cp":"61075","estado":"Michoacán","estado-slug":"michoacan","url":"https:\/\/cp.guiapaqueteria.com\/codigos-postales\/michoacan\/el-colorin\/"},{"colonia":"El Gigante","col-slug":"el-gigante","asentamiento":"Ranchería","cp":"61084","estado":"Michoacán","estado-slug":"michoacan","url":"https:\/\/cp.guiapaqueteria.com\/codigos-postales\/michoacan\/el-gigante\/"},{"colonia":"El Jazmín","col-slug":"el-jazmin","asentamiento":"Ranchería","cp":"61066","estado":"Michoacán","estado-slug":"michoacan","url":"https:\/\/cp.guiapaqueteria.com\/codigos-postales\/michoacan\/el-jazmin\/"},{"colonia":"El Llanito (Señor del Llano)","col-slug":"el-llanito-senor-del-llano","asentamiento":"Poblado comunal","cp":"61072","estado":"Michoacán","estado-slug":"michoacan","url":"https:\/\/cp.guiapaqueteria.com\/codigos-postales\/michoacan\/el-llanito-senor-del-llano\/"},{"colonia":"El Llanito Tlacotepec (Cuartel Tercero)","col-slug":"el-llanito-tlacotepec-cuartel-tercero","asentamiento":"Ranchería","cp":"61083","estado":"Michoacán","estado-slug":"michoacan","url":"https:\/\/cp.guiapaqueteria.com\/codigos-postales\/michoacan\/el-llanito-tlacotepec-cuartel-tercero\/"},{"colonia":"El Moral","col-slug":"el-moral","asentamiento":"Ranchería","cp":"61083","estado":"Michoacán","estado-slug":"michoacan","url":"https:\/\/cp.guiapaqueteria.com\/codigos-postales\/michoacan\/el-moral\/"},{"colonia":"El Real (El Real de Arriba)","col-slug":"el-real-el-real-de-arriba","asentamiento":"Ranchería","cp":"61062","estado":"Michoacán","estado-slug":"michoacan","url":"https:\/\/cp.guiapaqueteria.com\/codigos-postales\/michoacan\/el-real-el-real-de-arriba\/"},{"colonia":"Estanzuela (La Hacienda)","col-slug":"estanzuela-la-hacienda","asentamiento":"Ranchería","cp":"61065","estado":"Michoacán","estado-slug":"michoacan","url":"https:\/\/cp.guiapaqueteria.com\/codigos-postales\/michoacan\/estanzuela-la-hacienda\/"},{"colonia":"Guadalupe Victoria","col-slug":"guadalupe-victoria","asentamiento":"Pueblo","cp":"61075","estado":"Michoacán","estado-slug":"michoacan","url":"https:\/\/cp.guiapaqueteria.com\/codigos-postales\/michoacan\/guadalupe-victoria\/"},{"colonia":"Guanajuatito (Pintizuelas)","col-slug":"guanajuatito-pintizuelas","asentamiento":"Ranchería","cp":"61064","estado":"Michoacán","estado-slug":"michoacan","url":"https:\/\/cp.guiapaqueteria.com\/codigos-postales\/michoacan\/guanajuatito-pintizuelas\/"},{"colonia":"La América","col-slug":"la-america","asentamiento":"Ranchería","cp":"61083","estado":"Michoacán","estado-slug":"michoacan","url":"https:\/\/cp.guiapaqueteria.com\/codigos-postales\/michoacan\/la-america\/"},{"colonia":"La Granja","col-slug":"la-granja","asentamiento":"Ranchería","cp":"61084","estado":"Michoacán","estado-slug":"michoacan","url":"https:\/\/cp.guiapaqueteria.com\/codigos-postales\/michoacan\/la-granja\/"},{"colonia":"La Guerrita","col-slug":"la-guerrita","asentamiento":"Colonia","cp":"61060","estado":"Michoacán","estado-slug":"michoacan","url":"https:\/\/cp.guiapaqueteria.com\/codigos-postales\/michoacan\/la-guerrita\/"},{"colonia":"La Lagunilla","col-slug":"la-lagunilla","asentamiento":"Ranchería","cp":"61083","estado":"Michoacán","estado-slug":"michoacan","url":"https:\/\/cp.guiapaqueteria.com\/codigos-postales\/michoacan\/la-lagunilla\/"},{"colonia":"La Loma","col-slug":"la-loma","asentamiento":"Ranchería","cp":"61083","estado":"Michoacán","estado-slug":"michoacan","url":"https:\/\/cp.guiapaqueteria.com\/codigos-postales\/michoacan\/la-loma\/"},{"colonia":"La Lomita","col-slug":"la-lomita","asentamiento":"Ranchería","cp":"61062","estado":"Michoacán","estado-slug":"michoacan","url":"https:\/\/cp.guiapaqueteria.com\/codigos-postales\/michoacan\/la-lomita\/"},{"colonia":"La Lucha","col-slug":"la-lucha","asentamiento":"Colonia","cp":"61060","estado":"Michoacán","estado-slug":"michoacan","url":"https:\/\/cp.guiapaqueteria.com\/codigos-postales\/michoacan\/la-lucha\/"},{"colonia":"La Mesa","col-slug":"la-mesa","asentamiento":"Ranchería","cp":"61063","estado":"Michoacán","estado-slug":"michoacan","url":"https:\/\/cp.guiapaqueteria.com\/codigos-postales\/michoacan\/la-mesa\/"},{"colonia":"La Trampa","col-slug":"la-trampa","asentamiento":"Ranchería","cp":"61066","estado":"Michoacán","estado-slug":"michoacan","url":"https:\/\/cp.guiapaqueteria.com\/codigos-postales\/michoacan\/la-trampa\/"},{"colonia":"Las Canteras","col-slug":"las-canteras","asentamiento":"Ranchería","cp":"61073","estado":"Michoacán","estado-slug":"michoacan","url":"https:\/\/cp.guiapaqueteria.com\/codigos-postales\/michoacan\/las-canteras\/"},{"colonia":"Llano Grande Tlacotepec (Colonia Hidalgo)","col-slug":"llano-grande-tlacotepec-colonia-hidalgo","asentamiento":"Poblado comunal","cp":"61083","estado":"Michoacán","estado-slug":"michoacan","url":"https:\/\/cp.guiapaqueteria.com\/codigos-postales\/michoacan\/llano-grande-tlacotepec-colonia-hidalgo\/"},{"colonia":"Los Remedios","col-slug":"los-remedios","asentamiento":"Ranchería","cp":"61080","estado":"Michoacán","estado-slug":"michoacan","url":"https:\/\/cp.guiapaqueteria.com\/codigos-postales\/michoacan\/los-remedios\/"},{"colonia":"Los Reyes","col-slug":"los-reyes","asentamiento":"Ranchería","cp":"61075","estado":"Michoacán","estado-slug":"michoacan","url":"https:\/\/cp.guiapaqueteria.com\/codigos-postales\/michoacan\/los-reyes\/"},{"colonia":"Los Trejo (Santo Niño)","col-slug":"los-trejo-santo-nino","asentamiento":"Ranchería","cp":"61070","estado":"Michoacán","estado-slug":"michoacan","url":"https:\/\/cp.guiapaqueteria.com\/codigos-postales\/michoacan\/los-trejo-santo-nino\/"},{"colonia":"Monte Alegre","col-slug":"monte-alegre","asentamiento":"Ranchería","cp":"61082","estado":"Michoacán","estado-slug":"michoacan","url":"https:\/\/cp.guiapaqueteria.com\/codigos-postales\/michoacan\/monte-alegre\/"},{"colonia":"Palo Bonito","col-slug":"palo-bonito","asentamiento":"Ranchería","cp":"61063","estado":"Michoacán","estado-slug":"michoacan","url":"https:\/\/cp.guiapaqueteria.com\/codigos-postales\/michoacan\/palo-bonito\/"},{"colonia":"Parque del Águila (Cuartel Cuarto San Joaquín)","col-slug":"parque-del-aguila-cuartel-cuarto-san-joaquin","asentamiento":"Ranchería","cp":"61072","estado":"Michoacán","estado-slug":"michoacan","url":"https:\/\/cp.guiapaqueteria.com\/codigos-postales\/michoacan\/parque-del-aguila-cuartel-cuarto-san-joaquin\/"},{"colonia":"Planillas","col-slug":"planillas","asentamiento":"Ranchería","cp":"61080","estado":"Michoacán","estado-slug":"michoacan","url":"https:\/\/cp.guiapaqueteria.com\/codigos-postales\/michoacan\/planillas\/"},{"colonia":"Plaza de Gallos","col-slug":"plaza-de-gallos","asentamiento":"Ranchería","cp":"61066","estado":"Michoacán","estado-slug":"michoacan","url":"https:\/\/cp.guiapaqueteria.com\/codigos-postales\/michoacan\/plaza-de-gallos\/"},{"colonia":"Puente de Tierra","col-slug":"puente-de-tierra","asentamiento":"Ranchería","cp":"61074","estado":"Michoacán","estado-slug":"michoacan","url":"https:\/\/cp.guiapaqueteria.com\/codigos-postales\/michoacan\/puente-de-tierra\/"},{"colonia":"Puerto de Bermeo","col-slug":"puerto-de-bermeo","asentamiento":"Poblado comunal","cp":"61066","estado":"Michoacán","estado-slug":"michoacan","url":"https:\/\/cp.guiapaqueteria.com\/codigos-postales\/michoacan\/puerto-de-bermeo\/"},{"colonia":"Puerto de las Huertas (Ejido Tlalpujahuilla)","col-slug":"puerto-de-las-huertas-ejido-tlalpujahuilla","asentamiento":"Ranchería","cp":"61066","estado":"Michoacán","estado-slug":"michoacan","url":"https:\/\/cp.guiapaqueteria.com\/codigos-postales\/michoacan\/puerto-de-las-huertas-ejido-tlalpujahuilla\/"},{"colonia":"Puxtla","col-slug":"puxtla","asentamiento":"Colonia","cp":"61060","estado":"Michoacán","estado-slug":"michoacan","url":"https:\/\/cp.guiapaqueteria.com\/codigos-postales\/michoacan\/puxtla\/"},{"colonia":"Ramón Rayón","col-slug":"ramon-rayon","asentamiento":"Colonia","cp":"61060","estado":"Michoacán","estado-slug":"michoacan","url":"https:\/\/cp.guiapaqueteria.com\/codigos-postales\/michoacan\/ramon-rayon\/"},{"colonia":"Rincón del Sagrado Corazón (Rincón del Diablo)","col-slug":"rincon-del-sagrado-corazon-rincon-del-diablo","asentamiento":"Ranchería","cp":"61082","estado":"Michoacán","estado-slug":"michoacan","url":"https:\/\/cp.guiapaqueteria.com\/codigos-postales\/michoacan\/rincon-del-sagrado-corazon-rincon-del-diablo\/"},{"colonia":"Rosa de Castilla","col-slug":"rosa-de-castilla","asentamiento":"Ranchería","cp":"61075","estado":"Michoacán","estado-slug":"michoacan","url":"https:\/\/cp.guiapaqueteria.com\/codigos-postales\/michoacan\/rosa-de-castilla\/"},{"colonia":"San Francisco de los Reyes","col-slug":"san-francisco-de-los-reyes","asentamiento":"Pueblo","cp":"61070","estado":"Michoacán","estado-slug":"michoacan","url":"https:\/\/cp.guiapaqueteria.com\/codigos-postales\/michoacan\/san-francisco-de-los-reyes\/"},{"colonia":"San Isidro","col-slug":"san-isidro","asentamiento":"Ranchería","cp":"61072","estado":"Michoacán","estado-slug":"michoacan","url":"https:\/\/cp.guiapaqueteria.com\/codigos-postales\/michoacan\/san-isidro\/"},{"colonia":"San Joaquín Morelos","col-slug":"san-joaquin-morelos","asentamiento":"Ranchería","cp":"61072","estado":"Michoacán","estado-slug":"michoacan","url":"https:\/\/cp.guiapaqueteria.com\/codigos-postales\/michoacan\/san-joaquin-morelos\/"},{"colonia":"San José Corrales","col-slug":"san-jose-corrales","asentamiento":"Ranchería","cp":"61073","estado":"Michoacán","estado-slug":"michoacan","url":"https:\/\/cp.guiapaqueteria.com\/codigos-postales\/michoacan\/san-jose-corrales\/"},{"colonia":"San José de Guadalupe","col-slug":"san-jose-de-guadalupe","asentamiento":"Ejido","cp":"61074","estado":"Michoacán","estado-slug":"michoacan","url":"https:\/\/cp.guiapaqueteria.com\/codigos-postales\/michoacan\/san-jose-de-guadalupe\/"},{"colonia":"San Juan de Dios","col-slug":"san-juan-de-dios","asentamiento":"Poblado comunal","cp":"61064","estado":"Michoacán","estado-slug":"michoacan","url":"https:\/\/cp.guiapaqueteria.com\/codigos-postales\/michoacan\/san-juan-de-dios\/"},{"colonia":"San Juan Tlalpujahuilla (Tlalpujahuilla)","col-slug":"san-juan-tlalpujahuilla-tlalpujahuilla","asentamiento":"Pueblo","cp":"61062","estado":"Michoacán","estado-slug":"michoacan","url":"https:\/\/cp.guiapaqueteria.com\/codigos-postales\/michoacan\/san-juan-tlalpujahuilla-tlalpujahuilla\/"},{"colonia":"San Lorenzo Primer Cuartel (Los Mirtos)","col-slug":"san-lorenzo-primer-cuartel-los-mirtos","asentamiento":"Ranchería","cp":"61062","estado":"Michoacán","estado-slug":"michoacan","url":"https:\/\/cp.guiapaqueteria.com\/codigos-postales\/michoacan\/san-lorenzo-primer-cuartel-los-mirtos\/"},{"colonia":"San Lorenzo Segundo Cuartel","col-slug":"san-lorenzo-segundo-cuartel","asentamiento":"Poblado comunal","cp":"61062","estado":"Michoacán","estado-slug":"michoacan","url":"https:\/\/cp.guiapaqueteria.com\/codigos-postales\/michoacan\/san-lorenzo-segundo-cuartel\/"},{"colonia":"San Pedro Tarímbaro","col-slug":"san-pedro-tarimbaro","asentamiento":"Pueblo","cp":"61082","estado":"Michoacán","estado-slug":"michoacan","url":"https:\/\/cp.guiapaqueteria.com\/codigos-postales\/michoacan\/san-pedro-tarimbaro\/"},{"colonia":"San Rafael","col-slug":"san-rafael","asentamiento":"Ranchería","cp":"61073","estado":"Michoacán","estado-slug":"michoacan","url":"https:\/\/cp.guiapaqueteria.com\/codigos-postales\/michoacan\/san-rafael\/"},{"colonia":"Sandía","col-slug":"sandia","asentamiento":"Ranchería","cp":"61082","estado":"Michoacán","estado-slug":"michoacan","url":"https:\/\/cp.guiapaqueteria.com\/codigos-postales\/michoacan\/sandia\/"},{"colonia":"Santa Cruz","col-slug":"santa-cruz","asentamiento":"Ranchería","cp":"61064","estado":"Michoacán","estado-slug":"michoacan","url":"https:\/\/cp.guiapaqueteria.com\/codigos-postales\/michoacan\/santa-cruz\/"},{"colonia":"Santa María de los Ángeles","col-slug":"santa-maria-de-los-angeles","asentamiento":"Pueblo","cp":"61080","estado":"Michoacán","estado-slug":"michoacan","url":"https:\/\/cp.guiapaqueteria.com\/codigos-postales\/michoacan\/santa-maria-de-los-angeles\/"},{"colonia":"Tetela (Los Rodríguez)","col-slug":"tetela-los-rodriguez","asentamiento":"Ranchería","cp":"61070","estado":"Michoacán","estado-slug":"michoacan","url":"https:\/\/cp.guiapaqueteria.com\/codigos-postales\/michoacan\/tetela-los-rodriguez\/"},{"colonia":"Tierra Blanca","col-slug":"tierra-blanca","asentamiento":"Ranchería","cp":"61082","estado":"Michoacán","estado-slug":"michoacan","url":"https:\/\/cp.guiapaqueteria.com\/codigos-postales\/michoacan\/tierra-blanca\/"},{"colonia":"Tlacotepec","col-slug":"tlacotepec","asentamiento":"Pueblo","cp":"61067","estado":"Michoacán","estado-slug":"michoacan","url":"https:\/\/cp.guiapaqueteria.com\/codigos-postales\/michoacan\/tlacotepec\/"},{"colonia":"Tlalpujahua de Rayón","col-slug":"tlalpujahua-de-rayon","asentamiento":"Pueblo","cp":"61060","estado":"Michoacán","estado-slug":"michoacan","url":"https:\/\/cp.guiapaqueteria.com\/codigos-postales\/michoacan\/tlalpujahua-de-rayon\/"},{"colonia":"Trigueros","col-slug":"trigueros","asentamiento":"Colonia","cp":"61060","estado":"Michoacán","estado-slug":"michoacan","url":"https:\/\/cp.guiapaqueteria.com\/codigos-postales\/michoacan\/trigueros\/"},{"colonia":"Zapateros","col-slug":"zapateros","asentamiento":"Ranchería","cp":"61062","estado":"Michoacán","estado-slug":"michoacan","url":"https:\/\/cp.guiapaqueteria.com\/codigos-postales\/michoacan\/zapateros\/"}]