[{"colonia":"Amatenango del Valle","col-slug":"amatenango-del-valle","asentamiento":"Pueblo","cp":"29430","estado":"Chiapas","estado-slug":"chiapas","url":"https:\/\/cp.guiapaqueteria.com\/codigos-postales\/chiapas\/amatenango-del-valle\/"},{"colonia":"El Madronal","col-slug":"el-madronal","asentamiento":"Pueblo","cp":"29433","estado":"Chiapas","estado-slug":"chiapas","url":"https:\/\/cp.guiapaqueteria.com\/codigos-postales\/chiapas\/el-madronal\/"},{"colonia":"La Granada","col-slug":"la-granada","asentamiento":"Ranchería","cp":"29430","estado":"Chiapas","estado-slug":"chiapas","url":"https:\/\/cp.guiapaqueteria.com\/codigos-postales\/chiapas\/la-granada\/"},{"colonia":"La Grandeza","col-slug":"la-grandeza","asentamiento":"Pueblo","cp":"29432","estado":"Chiapas","estado-slug":"chiapas","url":"https:\/\/cp.guiapaqueteria.com\/codigos-postales\/chiapas\/la-grandeza\/"},{"colonia":"San Caralampio Chavín","col-slug":"san-caralampio-chavin","asentamiento":"Ranchería","cp":"29439","estado":"Chiapas","estado-slug":"chiapas","url":"https:\/\/cp.guiapaqueteria.com\/codigos-postales\/chiapas\/san-caralampio-chavin\/"},{"colonia":"San Vicente La Piedra","col-slug":"san-vicente-la-piedra","asentamiento":"Ranchería","cp":"29435","estado":"Chiapas","estado-slug":"chiapas","url":"https:\/\/cp.guiapaqueteria.com\/codigos-postales\/chiapas\/san-vicente-la-piedra\/"},{"colonia":"Unión Buenavista","col-slug":"union-buenavista","asentamiento":"Ranchería","cp":"29434","estado":"Chiapas","estado-slug":"chiapas","url":"https:\/\/cp.guiapaqueteria.com\/codigos-postales\/chiapas\/union-buenavista\/"}]