[{"colonia":"1o. de Diciembre","col-slug":"1o-de-diciembre","asentamiento":"Ranchería","cp":"37964","estado":"Guanajuato","estado-slug":"guanajuato","url":"https:\/\/cp.guiapaqueteria.com\/codigos-postales\/guanajuato\/1o-de-diciembre\/"},{"colonia":"Arroyo de la Plata (San Miguel)","col-slug":"arroyo-de-la-plata-san-miguel","asentamiento":"Ranchería","cp":"37965","estado":"Guanajuato","estado-slug":"guanajuato","url":"https:\/\/cp.guiapaqueteria.com\/codigos-postales\/guanajuato\/arroyo-de-la-plata-san-miguel\/"},{"colonia":"Begoña","col-slug":"begona","asentamiento":"Ranchería","cp":"37966","estado":"Guanajuato","estado-slug":"guanajuato","url":"https:\/\/cp.guiapaqueteria.com\/codigos-postales\/guanajuato\/begona\/"},{"colonia":"Bordo la Luz","col-slug":"bordo-la-luz","asentamiento":"Ranchería","cp":"37967","estado":"Guanajuato","estado-slug":"guanajuato","url":"https:\/\/cp.guiapaqueteria.com\/codigos-postales\/guanajuato\/bordo-la-luz\/"},{"colonia":"Carbonera de Guadalupe","col-slug":"carbonera-de-guadalupe","asentamiento":"Ranchería","cp":"37966","estado":"Guanajuato","estado-slug":"guanajuato","url":"https:\/\/cp.guiapaqueteria.com\/codigos-postales\/guanajuato\/carbonera-de-guadalupe\/"},{"colonia":"Cerrito de la Estancia (CerritoVerde)","col-slug":"cerrito-de-la-estancia-cerritoverde","asentamiento":"Ranchería","cp":"37967","estado":"Guanajuato","estado-slug":"guanajuato","url":"https:\/\/cp.guiapaqueteria.com\/codigos-postales\/guanajuato\/cerrito-de-la-estancia-cerritoverde\/"},{"colonia":"Cerro Chato","col-slug":"cerro-chato","asentamiento":"Ranchería","cp":"37967","estado":"Guanajuato","estado-slug":"guanajuato","url":"https:\/\/cp.guiapaqueteria.com\/codigos-postales\/guanajuato\/cerro-chato\/"},{"colonia":"Ciudad Dr. Mora Centro","col-slug":"ciudad-dr-mora-centro","asentamiento":"Colonia","cp":"37960","estado":"Guanajuato","estado-slug":"guanajuato","url":"https:\/\/cp.guiapaqueteria.com\/codigos-postales\/guanajuato\/ciudad-dr-mora-centro\/"},{"colonia":"Cuarto Blanco","col-slug":"cuarto-blanco","asentamiento":"Ranchería","cp":"37966","estado":"Guanajuato","estado-slug":"guanajuato","url":"https:\/\/cp.guiapaqueteria.com\/codigos-postales\/guanajuato\/cuarto-blanco\/"},{"colonia":"Derramadero de Charcas","col-slug":"derramadero-de-charcas","asentamiento":"Ranchería","cp":"37967","estado":"Guanajuato","estado-slug":"guanajuato","url":"https:\/\/cp.guiapaqueteria.com\/codigos-postales\/guanajuato\/derramadero-de-charcas\/"},{"colonia":"Derramadero de en Medio","col-slug":"derramadero-de-en-medio","asentamiento":"Ranchería","cp":"37967","estado":"Guanajuato","estado-slug":"guanajuato","url":"https:\/\/cp.guiapaqueteria.com\/codigos-postales\/guanajuato\/derramadero-de-en-medio\/"},{"colonia":"Derramadero del Sauz","col-slug":"derramadero-del-sauz","asentamiento":"Ranchería","cp":"37967","estado":"Guanajuato","estado-slug":"guanajuato","url":"https:\/\/cp.guiapaqueteria.com\/codigos-postales\/guanajuato\/derramadero-del-sauz\/"},{"colonia":"Ejidal J. Orduña","col-slug":"ejidal-j-orduna","asentamiento":"Ranchería","cp":"37964","estado":"Guanajuato","estado-slug":"guanajuato","url":"https:\/\/cp.guiapaqueteria.com\/codigos-postales\/guanajuato\/ejidal-j-orduna\/"},{"colonia":"Ejido Begoña","col-slug":"ejido-begona","asentamiento":"Ejido","cp":"37967","estado":"Guanajuato","estado-slug":"guanajuato","url":"https:\/\/cp.guiapaqueteria.com\/codigos-postales\/guanajuato\/ejido-begona\/"},{"colonia":"Ejido Vagui","col-slug":"ejido-vagui","asentamiento":"Ejido","cp":"37965","estado":"Guanajuato","estado-slug":"guanajuato","url":"https:\/\/cp.guiapaqueteria.com\/codigos-postales\/guanajuato\/ejido-vagui\/"},{"colonia":"El Baño","col-slug":"el-bano","asentamiento":"Ranchería","cp":"37966","estado":"Guanajuato","estado-slug":"guanajuato","url":"https:\/\/cp.guiapaqueteria.com\/codigos-postales\/guanajuato\/el-bano\/"},{"colonia":"El Carmen","col-slug":"el-carmen","asentamiento":"Ranchería","cp":"37967","estado":"Guanajuato","estado-slug":"guanajuato","url":"https:\/\/cp.guiapaqueteria.com\/codigos-postales\/guanajuato\/el-carmen\/"},{"colonia":"El Lindero","col-slug":"el-lindero","asentamiento":"Ranchería","cp":"37967","estado":"Guanajuato","estado-slug":"guanajuato","url":"https:\/\/cp.guiapaqueteria.com\/codigos-postales\/guanajuato\/el-lindero\/"},{"colonia":"El Mezquite","col-slug":"el-mezquite","asentamiento":"Ranchería","cp":"37966","estado":"Guanajuato","estado-slug":"guanajuato","url":"https:\/\/cp.guiapaqueteria.com\/codigos-postales\/guanajuato\/el-mezquite\/"},{"colonia":"El Mirto","col-slug":"el-mirto","asentamiento":"Ranchería","cp":"37966","estado":"Guanajuato","estado-slug":"guanajuato","url":"https:\/\/cp.guiapaqueteria.com\/codigos-postales\/guanajuato\/el-mirto\/"},{"colonia":"El Paraíso","col-slug":"el-paraiso","asentamiento":"Colonia","cp":"37964","estado":"Guanajuato","estado-slug":"guanajuato","url":"https:\/\/cp.guiapaqueteria.com\/codigos-postales\/guanajuato\/el-paraiso\/"},{"colonia":"El Ramillete","col-slug":"el-ramillete","asentamiento":"Ranchería","cp":"37966","estado":"Guanajuato","estado-slug":"guanajuato","url":"https:\/\/cp.guiapaqueteria.com\/codigos-postales\/guanajuato\/el-ramillete\/"},{"colonia":"El Tepetate","col-slug":"el-tepetate","asentamiento":"Ranchería","cp":"37967","estado":"Guanajuato","estado-slug":"guanajuato","url":"https:\/\/cp.guiapaqueteria.com\/codigos-postales\/guanajuato\/el-tepetate\/"},{"colonia":"Escalante","col-slug":"escalante","asentamiento":"Ranchería","cp":"37967","estado":"Guanajuato","estado-slug":"guanajuato","url":"https:\/\/cp.guiapaqueteria.com\/codigos-postales\/guanajuato\/escalante\/"},{"colonia":"Jesús María","col-slug":"jesus-maria","asentamiento":"Ranchería","cp":"37967","estado":"Guanajuato","estado-slug":"guanajuato","url":"https:\/\/cp.guiapaqueteria.com\/codigos-postales\/guanajuato\/jesus-maria\/"},{"colonia":"La Aldea","col-slug":"la-aldea","asentamiento":"Ranchería","cp":"37967","estado":"Guanajuato","estado-slug":"guanajuato","url":"https:\/\/cp.guiapaqueteria.com\/codigos-postales\/guanajuato\/la-aldea\/"},{"colonia":"La Barranca","col-slug":"la-barranca","asentamiento":"Ranchería","cp":"37966","estado":"Guanajuato","estado-slug":"guanajuato","url":"https:\/\/cp.guiapaqueteria.com\/codigos-postales\/guanajuato\/la-barranca\/"},{"colonia":"La Cantera","col-slug":"la-cantera","asentamiento":"Ranchería","cp":"37963","estado":"Guanajuato","estado-slug":"guanajuato","url":"https:\/\/cp.guiapaqueteria.com\/codigos-postales\/guanajuato\/la-cantera\/"},{"colonia":"La Doncella","col-slug":"la-doncella","asentamiento":"Ranchería","cp":"37967","estado":"Guanajuato","estado-slug":"guanajuato","url":"https:\/\/cp.guiapaqueteria.com\/codigos-postales\/guanajuato\/la-doncella\/"},{"colonia":"La Estancia (El Cerrito)","col-slug":"la-estancia-el-cerrito","asentamiento":"Ranchería","cp":"37966","estado":"Guanajuato","estado-slug":"guanajuato","url":"https:\/\/cp.guiapaqueteria.com\/codigos-postales\/guanajuato\/la-estancia-el-cerrito\/"},{"colonia":"La Fortuna","col-slug":"la-fortuna","asentamiento":"Colonia","cp":"37967","estado":"Guanajuato","estado-slug":"guanajuato","url":"https:\/\/cp.guiapaqueteria.com\/codigos-postales\/guanajuato\/la-fortuna\/"},{"colonia":"La Laguna","col-slug":"la-laguna","asentamiento":"Ranchería","cp":"37966","estado":"Guanajuato","estado-slug":"guanajuato","url":"https:\/\/cp.guiapaqueteria.com\/codigos-postales\/guanajuato\/la-laguna\/"},{"colonia":"La Noria","col-slug":"la-noria","asentamiento":"Pueblo","cp":"37967","estado":"Guanajuato","estado-slug":"guanajuato","url":"https:\/\/cp.guiapaqueteria.com\/codigos-postales\/guanajuato\/la-noria\/"},{"colonia":"La Otra Banda","col-slug":"la-otra-banda","asentamiento":"Ranchería","cp":"37963","estado":"Guanajuato","estado-slug":"guanajuato","url":"https:\/\/cp.guiapaqueteria.com\/codigos-postales\/guanajuato\/la-otra-banda\/"},{"colonia":"La Otra Banda (Juan Galván Vázquez)","col-slug":"la-otra-banda-juan-galvan-vazquez","asentamiento":"Granja","cp":"37965","estado":"Guanajuato","estado-slug":"guanajuato","url":"https:\/\/cp.guiapaqueteria.com\/codigos-postales\/guanajuato\/la-otra-banda-juan-galvan-vazquez\/"},{"colonia":"La Presa del Gato","col-slug":"la-presa-del-gato","asentamiento":"Ranchería","cp":"37965","estado":"Guanajuato","estado-slug":"guanajuato","url":"https:\/\/cp.guiapaqueteria.com\/codigos-postales\/guanajuato\/la-presa-del-gato\/"},{"colonia":"La Purísima","col-slug":"la-purisima","asentamiento":"Ranchería","cp":"37967","estado":"Guanajuato","estado-slug":"guanajuato","url":"https:\/\/cp.guiapaqueteria.com\/codigos-postales\/guanajuato\/la-purisima\/"},{"colonia":"La Redonda","col-slug":"la-redonda","asentamiento":"Ranchería","cp":"37967","estado":"Guanajuato","estado-slug":"guanajuato","url":"https:\/\/cp.guiapaqueteria.com\/codigos-postales\/guanajuato\/la-redonda\/"},{"colonia":"La Tinaja","col-slug":"la-tinaja","asentamiento":"Ranchería","cp":"37967","estado":"Guanajuato","estado-slug":"guanajuato","url":"https:\/\/cp.guiapaqueteria.com\/codigos-postales\/guanajuato\/la-tinaja\/"},{"colonia":"Las Flores","col-slug":"las-flores","asentamiento":"Ranchería","cp":"37966","estado":"Guanajuato","estado-slug":"guanajuato","url":"https:\/\/cp.guiapaqueteria.com\/codigos-postales\/guanajuato\/las-flores\/"},{"colonia":"Las Palmitas","col-slug":"las-palmitas","asentamiento":"Ranchería","cp":"37967","estado":"Guanajuato","estado-slug":"guanajuato","url":"https:\/\/cp.guiapaqueteria.com\/codigos-postales\/guanajuato\/las-palmitas\/"},{"colonia":"Loma de Buenavista","col-slug":"loma-de-buenavista","asentamiento":"Ranchería","cp":"37965","estado":"Guanajuato","estado-slug":"guanajuato","url":"https:\/\/cp.guiapaqueteria.com\/codigos-postales\/guanajuato\/loma-de-buenavista\/"},{"colonia":"Loma del Zapote","col-slug":"loma-del-zapote","asentamiento":"Ranchería","cp":"37967","estado":"Guanajuato","estado-slug":"guanajuato","url":"https:\/\/cp.guiapaqueteria.com\/codigos-postales\/guanajuato\/loma-del-zapote\/"},{"colonia":"Loreto","col-slug":"loreto","asentamiento":"Granja","cp":"37967","estado":"Guanajuato","estado-slug":"guanajuato","url":"https:\/\/cp.guiapaqueteria.com\/codigos-postales\/guanajuato\/loreto\/"},{"colonia":"Los Amoles","col-slug":"los-amoles","asentamiento":"Ranchería","cp":"37966","estado":"Guanajuato","estado-slug":"guanajuato","url":"https:\/\/cp.guiapaqueteria.com\/codigos-postales\/guanajuato\/los-amoles\/"},{"colonia":"Los Duraznos","col-slug":"los-duraznos","asentamiento":"Ranchería","cp":"37965","estado":"Guanajuato","estado-slug":"guanajuato","url":"https:\/\/cp.guiapaqueteria.com\/codigos-postales\/guanajuato\/los-duraznos\/"},{"colonia":"Los Tejados","col-slug":"los-tejados","asentamiento":"Ranchería","cp":"37966","estado":"Guanajuato","estado-slug":"guanajuato","url":"https:\/\/cp.guiapaqueteria.com\/codigos-postales\/guanajuato\/los-tejados\/"},{"colonia":"Majada Verde","col-slug":"majada-verde","asentamiento":"Ranchería","cp":"37966","estado":"Guanajuato","estado-slug":"guanajuato","url":"https:\/\/cp.guiapaqueteria.com\/codigos-postales\/guanajuato\/majada-verde\/"},{"colonia":"Morisquillas","col-slug":"morisquillas","asentamiento":"Ranchería","cp":"37967","estado":"Guanajuato","estado-slug":"guanajuato","url":"https:\/\/cp.guiapaqueteria.com\/codigos-postales\/guanajuato\/morisquillas\/"},{"colonia":"Negritas","col-slug":"negritas","asentamiento":"Ranchería","cp":"37967","estado":"Guanajuato","estado-slug":"guanajuato","url":"https:\/\/cp.guiapaqueteria.com\/codigos-postales\/guanajuato\/negritas\/"},{"colonia":"Obrajitos de Abajo","col-slug":"obrajitos-de-abajo","asentamiento":"Ranchería","cp":"37966","estado":"Guanajuato","estado-slug":"guanajuato","url":"https:\/\/cp.guiapaqueteria.com\/codigos-postales\/guanajuato\/obrajitos-de-abajo\/"},{"colonia":"Obrajitos de Arriba","col-slug":"obrajitos-de-arriba","asentamiento":"Ranchería","cp":"37966","estado":"Guanajuato","estado-slug":"guanajuato","url":"https:\/\/cp.guiapaqueteria.com\/codigos-postales\/guanajuato\/obrajitos-de-arriba\/"},{"colonia":"Obrajitos de en Enmedio","col-slug":"obrajitos-de-en-enmedio","asentamiento":"Ranchería","cp":"37966","estado":"Guanajuato","estado-slug":"guanajuato","url":"https:\/\/cp.guiapaqueteria.com\/codigos-postales\/guanajuato\/obrajitos-de-en-enmedio\/"},{"colonia":"Peña Rodada","col-slug":"pena-rodada","asentamiento":"Ranchería","cp":"37966","estado":"Guanajuato","estado-slug":"guanajuato","url":"https:\/\/cp.guiapaqueteria.com\/codigos-postales\/guanajuato\/pena-rodada\/"},{"colonia":"Peñitas","col-slug":"penitas","asentamiento":"Ranchería","cp":"37966","estado":"Guanajuato","estado-slug":"guanajuato","url":"https:\/\/cp.guiapaqueteria.com\/codigos-postales\/guanajuato\/penitas\/"},{"colonia":"Presa de los Duraznos","col-slug":"presa-de-los-duraznos","asentamiento":"Granja","cp":"37965","estado":"Guanajuato","estado-slug":"guanajuato","url":"https:\/\/cp.guiapaqueteria.com\/codigos-postales\/guanajuato\/presa-de-los-duraznos\/"},{"colonia":"Puerta de la Barranca","col-slug":"puerta-de-la-barranca","asentamiento":"Ranchería","cp":"37965","estado":"Guanajuato","estado-slug":"guanajuato","url":"https:\/\/cp.guiapaqueteria.com\/codigos-postales\/guanajuato\/puerta-de-la-barranca\/"},{"colonia":"Puerta del Pedregal (Santo Niño)","col-slug":"puerta-del-pedregal-santo-nino","asentamiento":"Ranchería","cp":"37965","estado":"Guanajuato","estado-slug":"guanajuato","url":"https:\/\/cp.guiapaqueteria.com\/codigos-postales\/guanajuato\/puerta-del-pedregal-santo-nino\/"},{"colonia":"Puerto de la Oveja","col-slug":"puerto-de-la-oveja","asentamiento":"Ranchería","cp":"37967","estado":"Guanajuato","estado-slug":"guanajuato","url":"https:\/\/cp.guiapaqueteria.com\/codigos-postales\/guanajuato\/puerto-de-la-oveja\/"},{"colonia":"Puerto de Trojes (La Troje)","col-slug":"puerto-de-trojes-la-troje","asentamiento":"Ranchería","cp":"37965","estado":"Guanajuato","estado-slug":"guanajuato","url":"https:\/\/cp.guiapaqueteria.com\/codigos-postales\/guanajuato\/puerto-de-trojes-la-troje\/"},{"colonia":"Puerto del Obispo de Abajo","col-slug":"puerto-del-obispo-de-abajo","asentamiento":"Ranchería","cp":"37965","estado":"Guanajuato","estado-slug":"guanajuato","url":"https:\/\/cp.guiapaqueteria.com\/codigos-postales\/guanajuato\/puerto-del-obispo-de-abajo\/"},{"colonia":"Puerto del Obispo de Arriba","col-slug":"puerto-del-obispo-de-arriba","asentamiento":"Ranchería","cp":"37965","estado":"Guanajuato","estado-slug":"guanajuato","url":"https:\/\/cp.guiapaqueteria.com\/codigos-postales\/guanajuato\/puerto-del-obispo-de-arriba\/"},{"colonia":"Ranchito de San José","col-slug":"ranchito-de-san-jose","asentamiento":"Ranchería","cp":"37965","estado":"Guanajuato","estado-slug":"guanajuato","url":"https:\/\/cp.guiapaqueteria.com\/codigos-postales\/guanajuato\/ranchito-de-san-jose\/"},{"colonia":"Rancho Nuevo de Guadalupe (El Hurón)","col-slug":"rancho-nuevo-de-guadalupe-el-huron","asentamiento":"Ranchería","cp":"37965","estado":"Guanajuato","estado-slug":"guanajuato","url":"https:\/\/cp.guiapaqueteria.com\/codigos-postales\/guanajuato\/rancho-nuevo-de-guadalupe-el-huron\/"},{"colonia":"Sacromonte","col-slug":"sacromonte","asentamiento":"Ranchería","cp":"37965","estado":"Guanajuato","estado-slug":"guanajuato","url":"https:\/\/cp.guiapaqueteria.com\/codigos-postales\/guanajuato\/sacromonte\/"},{"colonia":"San Agustín","col-slug":"san-agustin","asentamiento":"Ranchería","cp":"37967","estado":"Guanajuato","estado-slug":"guanajuato","url":"https:\/\/cp.guiapaqueteria.com\/codigos-postales\/guanajuato\/san-agustin\/"},{"colonia":"San Antonio Tercero","col-slug":"san-antonio-tercero","asentamiento":"Ranchería","cp":"37966","estado":"Guanajuato","estado-slug":"guanajuato","url":"https:\/\/cp.guiapaqueteria.com\/codigos-postales\/guanajuato\/san-antonio-tercero\/"},{"colonia":"San Francisco del Álamo","col-slug":"san-francisco-del-alamo","asentamiento":"Granja","cp":"37967","estado":"Guanajuato","estado-slug":"guanajuato","url":"https:\/\/cp.guiapaqueteria.com\/codigos-postales\/guanajuato\/san-francisco-del-alamo\/"},{"colonia":"San Jerónimo del Mezquital","col-slug":"san-jeronimo-del-mezquital","asentamiento":"Ranchería","cp":"37966","estado":"Guanajuato","estado-slug":"guanajuato","url":"https:\/\/cp.guiapaqueteria.com\/codigos-postales\/guanajuato\/san-jeronimo-del-mezquital\/"},{"colonia":"San Rafael","col-slug":"san-rafael","asentamiento":"Ranchería","cp":"37967","estado":"Guanajuato","estado-slug":"guanajuato","url":"https:\/\/cp.guiapaqueteria.com\/codigos-postales\/guanajuato\/san-rafael\/"},{"colonia":"San Vicente","col-slug":"san-vicente","asentamiento":"Ranchería","cp":"37967","estado":"Guanajuato","estado-slug":"guanajuato","url":"https:\/\/cp.guiapaqueteria.com\/codigos-postales\/guanajuato\/san-vicente\/"},{"colonia":"Santa Cruz","col-slug":"santa-cruz","asentamiento":"Granja","cp":"37967","estado":"Guanajuato","estado-slug":"guanajuato","url":"https:\/\/cp.guiapaqueteria.com\/codigos-postales\/guanajuato\/santa-cruz\/"},{"colonia":"Tierra Prieta","col-slug":"tierra-prieta","asentamiento":"Ranchería","cp":"37965","estado":"Guanajuato","estado-slug":"guanajuato","url":"https:\/\/cp.guiapaqueteria.com\/codigos-postales\/guanajuato\/tierra-prieta\/"},{"colonia":"Vagui","col-slug":"vagui","asentamiento":"Ranchería","cp":"37965","estado":"Guanajuato","estado-slug":"guanajuato","url":"https:\/\/cp.guiapaqueteria.com\/codigos-postales\/guanajuato\/vagui\/"}]